lab06dig/E6/E1/E1.v
//José Alejandro Rodríguez Porras 19131
//Electrónica Digital
//Laboratorio 6
//Ejercicio 6: Ejercicio 1
// Flip Flop Tipo D con reset asíncrono y
module dff(input clk, rst, d, output reg q);

    always @ (posedge clk or posedge rst) begin
        if (rst)
            q <= 1'b0;
        else
            q <= d;
    end
endmodule
//Módulo de la FSM de Mealy del ejercicio 1
module E_1(input clk, rst, A, B, output S1, S0, SF1, SF0, output Y);
    //estaos presentes y futuros
    wire S1, S0, SF1, SF0;
    //asignación del estado futuro con sus respectivas ecuaciones minimizadas
    assign SF1 = (S1 & A & B) | (S0 & B);
    assign SF0 = (~S1 & ~S0 & A);
    //creación de cada flip flop para cada estado futuro y su respectiva asignación de variables al módulo
    dff FF1(clk, rst, SF1, S1);
    dff FF0(clk, rst, SF0, S0);
    //asignación de la salida de la máquina con su ecuación minimizada
    assign Y = (S1 & A & B);
endmodule

lab06dig/E6/E1/E1_tb.v
//Alejandro Rodríguez 19131
//Lab 6
//testbench
//Ejercicio 1
module testbench();
    reg clk, rst, A, B;
    wire Y, S1, S0, SF1, SF0;
    E_1 e1(clk, rst, A, B, S1, S0, SF1, SF0, Y);
    initial begin
    $display("clk rst A B S1 S0 SF1 SF0 | Y");
    $display("--------------------------|--");
    $monitor("%b %b %b %b %b %b %b %b| %b", clk, rst, A, B, S1, S0, SF1, SF0, Y);
 // Prueba del funcionamiento de la máquina con las distintas combinaciones para que cambie a cada uno de los estados 
        clk = 0; rst = 0; A = 0; B = 0;
        #1 rst = 1;
        #1 rst = 0;
        #3 A = 1; B = 0;
        #3 A = 0; B = 1;
        #3 A = 1; B = 1;
        //Prueba del reset asíncrono en un flanco negativo
        #1 rst = 1;
        #1 rst = 0;
        #3 A = 1; B = 0;
        #3 A = 0; B = 0;
        #3 A = 0; B = 0;
        #3 A = 1; B = 1;
        #50 $finish;
    end 
    //generación del reloj con período de 4 unidades de tiempo
    always
        #2 clk = ~clk;
    initial begin
        $dumpfile("E1_tb.vcd");
        $dumpvars(0,testbench);
    end
endmodule

lab06dig/E6/E1/E1_tb.vcd
$date
	Sat Sep 05 22:37:40 2020
$end
$version
	Icarus Verilog
$end
$timescale
	1ps
$end
$scope module testbench $end
$var wire 1 ! Y $end
$var wire 1 " SF1 $end
$var wire 1 # SF0 $end
$var wire 1 $ S1 $end
$var wire 1 % S0 $end
$var reg 1 & A $end
$var reg 1 ' B $end
$var reg 1 ( clk $end
$var reg 1 ) rst $end
$scope module e1 $end
$var wire 1 & A $end
$var wire 1 ' B $end
$var wire 1 # SF0 $end
$var wire 1 " SF1 $end
$var wire 1 ! Y $end
$var wire 1 ( clk $end
$var wire 1 ) rst $end
$var wire 1 $ S1 $end
$var wire 1 % S0 $end
$scope module FF0 $end
$var wire 1 ( clk $end
$var wire 1 # d $end
$var wire 1 ) rst $end
$var reg 1 % q $end
$upscope $end
$scope module FF1 $end
$var wire 1 ( clk $end
$var wire 1 " d $end
$var wire 1 ) rst $end
$var reg 1 $ q $end
$upscope $end
$upscope $end
$upscope $end
$enddefinitions $end
#0
$dumpvars
0)
0(
0'
0&
x%
x$
0#
0"
0!
$end
#1
0$
0%
1)
#2
0)
1(
#4
0(
#5
1#
1&
#6
0#
1%
1(
#8
1"
0(
1'
0&
#10
0"
0%
1$
1(
#11
1"
1!
1&
#12
1#
0"
0!
0$
1)
0(
#13
0)
#14
0#
1"
1%
1(
#16
0"
0(
0'
#18
1#
0%
1(
#19
0#
0&
#20
0(
#22
1(
#24
0(
#25
1#
1'
1&
#26
0#
1"
1%
1(
#28
0(
#30
1!
0%
1$
1(
