lab03dig/t03sop/t03sop.v
//Alejandro Rodríguez 19131
//Lab 3 t3 sop
module gates(); //creación de módulo
//variables
reg A,B,C,D; //in variables
wire w1,w2,w3,w4,w5,w6,w7; //or out variables
wire n1,n2,n3,n4; //not out variables
wire r1; //and out variable
not PnA(n1,A); //not gates para A, B, C y D
not PnB(n2,B);
not PnC(n3,C);
not PnD(n4,D);
and Pw1(w1,n1,n2,n3,n4);//A'B'C'D
and Pw2(w2,n1,n2,n3,D);//A'B'C'D
and Pw3(w3,n2,n2,C,n4);//A'B'CD'
and Pw4(w4,n1,n2,C,D);//A'B'CD
and Pw5(w5,A,n2,n3,n4);//A'B'C'D'
and Pw6(w6,A,n2,C,n4);//AB'CD'
and Pw7(w7,A,B,C,n4);//ABCD'
or Pr1(r1,w1,w2,w3,w4,w5,w6,w7);//Y3
//comienzo
initial begin
    $display("A B C D | Y");
    $display("-----------");
    $monitor("%b %b %b %b | %b", A, B, C, D, r1);
    //condición inicial
    A = 0; B = 0; C = 0; D = 0;
    //simulación combinaciones
    #1 D = 1;
    #1 C = 1; D = 0;
    #1 D = 1;
    #1 B = 1; C = 0; D = 0;
    #1 D = 1;
    #1 C = 1; D = 0;
    #1 D = 1;
    #1 A = 1; B = 0; C = 0; D = 0;
    #1 D = 1;
    #1 C = 1; D = 0;
    #1 D = 1;
    #1 B = 1; C = 0; D = 0;
    #1 D = 1;
    #1 C = 1; D = 0;
    #1 D = 1;
    #1 $finish; //final de la simulación
end
initial
    begin
        $dumpfile("t03sop_tb.vcd"); //se crea archivo vcd
        $dumpvars(0,gates);
    end
endmodule //fin del módulo

lab03dig/t03sop/t03sop_tb.vcd
$date
	Fri Jul 31 22:55:49 2020
$end
$version
	Icarus Verilog
$end
$timescale
	1ps
$end
$scope module gates $end
$var wire 1 ! n1 $end
$var wire 1 " n2 $end
$var wire 1 # n3 $end
$var wire 1 $ n4 $end
$var wire 1 % r1 $end
$var wire 1 & w1 $end
$var wire 1 ' w2 $end
$var wire 1 ( w3 $end
$var wire 1 ) w4 $end
$var wire 1 * w5 $end
$var wire 1 + w6 $end
$var wire 1 , w7 $end
$var reg 1 - A $end
$var reg 1 . B $end
$var reg 1 / C $end
$var reg 1 0 D $end
$upscope $end
$enddefinitions $end
#0
$dumpvars
00
0/
0.
0-
0,
0+
0*
0)
0(
0'
1&
1%
1$
1#
1"
1!
$end
#1
0&
1'
0$
10
#2
1(
0'
1$
0#
00
1/
#3
0(
1)
0$
10
#4
0%
1$
0)
1#
0"
00
0/
1.
#5
0$
10
#6
1$
0#
00
1/
#7
0$
10
#8
1%
1*
1$
1#
1"
0!
00
0/
0.
1-
#9
0%
0*
0$
10
#10
1%
1(
1+
1$
0#
00
1/
#11
0%
0(
0+
0$
10
#12
1$
1#
0"
00
0/
1.
#13
0$
10
#14
1%
1,
1$
0#
00
1/
#15
0%
0,
0$
10
