lab06dig/E6/E3/E3.v
//José Alejandro Rodríguez Porras 19131
//Electrónica Digital
//Laboratorio 6
//Ejercicio 6: Ejercicio 3
// Flip Flop Tipo D con reset asíncrono de un bit
module dff(input clk, rst, d, output reg q);

    always @ (posedge clk or posedge rst)
        if (rst)
            q <= 1'b0; 
        else begin
            q <= d;
    end
endmodule
//módulo de la FSM de Moore del contador de Gray (Ejercicio 3)
module E_3(input clk, rst, A, output S2, S1, S0, SF2, SF1, SF0, Y2, Y1, Y0);
    //salidas de estados presentes y futuros
    wire S2, S1, S0, SF2, SF1, SF0;
    //asignación de cada estado futuro con su ecuación minimizada
    assign SF2 = (~S2 & S1 & S0 & A) | (~S2 & ~S1 & ~S0 & ~A) | (S2 & S0 & ~A) | (S2 & ~S1 & A) | (S2 & S1 & ~S0);
    assign SF1 = (S1 & S0 & ~A) | (~S1 & S0 & A) | (~S1 & ~S0 & ~A) | (S1 & ~S0 & A);
    assign SF0 = ~S0;
    //creación de los flip flops para cada estado y asignación de variables a cada módulo
    dff FF2(clk, rst, SF2, S2);
    dff FF1(clk, rst, SF1, S1);
    dff FF0(clk, rst, SF0, S0);
    //asignación de las salidas de la fsm con sus ecuaciones minimizadas
    assign Y2 = S2;
    assign Y1 = (~S2 & S1) | (S2 & ~S1);
    assign Y0 = (S1 & ~S0) | (~S1 & S0);
endmodule

lab06dig/E6/E3/E3_tb.v
//Alejandro Rodríguez 19131
//Lab 6
//testbench
//Ejercicio 3
module testbench();
    reg clk, rst, A;
    wire Y2, Y1, Y0, S2, S1, S0, SF2, SF1, SF0;
    E_3 e3(clk, rst, A, S2, S1, S0, SF2, SF1, SF0, Y2, Y1, Y0);
    initial begin
    $display("S2 S1 S0 SF2 SF1 SF0 | Y2 Y1 Y0");
    $display("------------------|----------");
    $monitor("%b %b %b %b %b %b | %b %b %b", clk, rst, A, S2, S1, S0, SF2, SF1, SF0, Y2, Y1, Y0);
 // Prueba del funcionamiento de la máquina completa, comienza el contador de Gray
        clk = 0; rst = 0; A = 0;
        #1 rst = 1;
        #1 rst = 0;
        #3 A = 1;
        //Prueba del reset asíncrono 
        #31 rst = 1;
        #1 rst = 0;
        #1 A = 1;
        //Se pone en modo reversa
        #5 A = 0;
        #100 $finish;
    end 
    //generación del reloj con período de 4 unidades de tiempo
    always
        #2 clk = ~clk;
        //creación del archivo vcd
    initial begin
        $dumpfile("E3_tb.vcd");
        $dumpvars(0,testbench);
    end
endmodule

lab06dig/E6/E3/E3_tb.vcd
$date
	Sat Sep 05 22:30:09 2020
$end
$version
	Icarus Verilog
$end
$timescale
	1ps
$end
$scope module testbench $end
$var wire 1 ! Y2 $end
$var wire 1 " Y1 $end
$var wire 1 # Y0 $end
$var wire 1 $ SF2 $end
$var wire 1 % SF1 $end
$var wire 1 & SF0 $end
$var wire 1 ' S2 $end
$var wire 1 ( S1 $end
$var wire 1 ) S0 $end
$var reg 1 * A $end
$var reg 1 + clk $end
$var reg 1 , rst $end
$scope module e3 $end
$var wire 1 * A $end
$var wire 1 & SF0 $end
$var wire 1 % SF1 $end
$var wire 1 $ SF2 $end
$var wire 1 # Y0 $end
$var wire 1 " Y1 $end
$var wire 1 ! Y2 $end
$var wire 1 + clk $end
$var wire 1 , rst $end
$var wire 1 ' S2 $end
$var wire 1 ( S1 $end
$var wire 1 ) S0 $end
$scope module FF0 $end
$var wire 1 + clk $end
$var wire 1 & d $end
$var wire 1 , rst $end
$var reg 1 ) q $end
$upscope $end
$scope module FF1 $end
$var wire 1 + clk $end
$var wire 1 % d $end
$var wire 1 , rst $end
$var reg 1 ( q $end
$upscope $end
$scope module FF2 $end
$var wire 1 + clk $end
$var wire 1 $ d $end
$var wire 1 , rst $end
$var reg 1 ' q $end
$upscope $end
$upscope $end
$upscope $end
$enddefinitions $end
#0
$dumpvars
0,
0+
0*
x)
x(
x'
x&
x%
x$
x#
x"
x!
$end
#1
1$
1%
0"
0#
1&
0!
0'
0(
0)
1,
#2
0#
0"
0&
1)
1(
1!
1'
0,
1+
#4
0+
#5
0$
0%
1*
#6
1&
0!
0'
0(
0)
1+
#8
0+
#10
1%
1#
0&
1)
1+
#12
0+
#14
1"
1&
1(
0)
1+
#16
0+
#18
1$
0%
0#
0&
1)
1+
#20
0+
#22
1&
1!
1'
0(
0)
1+
#24
0+
#26
1%
1#
0&
1)
1+
#28
0+
#30
0"
1&
1(
0)
1+
#32
0+
#34
0%
0#
0$
0&
1)
1+
#36
1&
0!
0'
0(
0)
0+
1,
#37
0,
#38
1%
1#
0&
1)
1+
#40
0+
#42
1"
1&
1(
0)
1+
#43
0%
0*
#44
0+
#46
0"
0&
1)
0(
1+
#48
0+
#50
1$
1%
0#
1&
0)
1+
#52
0+
#54
0#
0"
0&
1)
1(
1!
1'
1+
#56
0+
#58
0%
1#
1&
0)
1+
#60
0+
#62
1"
1$
0&
1)
0(
1+
#64
0+
#66
1%
0$
0#
1&
0)
1+
#68
0+
#70
0#
0&
1)
1(
0!
0'
1+
#72
0+
#74
0%
1#
1&
0)
1+
#76
0+
#78
0"
0&
1)
0(
1+
#80
0+
#82
1$
1%
0#
1&
0)
1+
#84
0+
#86
0#
0"
0&
1)
1(
1!
1'
1+
#88
0+
#90
0%
1#
1&
0)
1+
#92
0+
#94
1"
1$
0&
1)
0(
1+
#96
0+
#98
1%
0$
0#
1&
0)
1+
#100
0+
#102
0#
0&
1)
1(
0!
0'
1+
#104
0+
#106
0%
1#
1&
0)
1+
#108
0+
#110
0"
0&
1)
0(
1+
#112
0+
#114
1$
1%
0#
1&
0)
1+
#116
0+
#118
0#
0"
0&
1)
1(
1!
1'
1+
#120
0+
#122
0%
1#
1&
0)
1+
#124
0+
#126
1"
1$
0&
1)
0(
1+
#128
0+
#130
1%
0$
0#
1&
0)
1+
#132
0+
#134
0#
0&
1)
1(
0!
0'
1+
#136
0+
#138
0%
1#
1&
0)
1+
#140
0+
#142
0"
0&
1)
0(
1+
