lab09dig/E5/E5.v
//José Alejandro Rodríguez Porras 19131
//Electrónica Digital 1
//Laboratorio 9
//Ejercicio 5
//Memoria ROM 
module ROM(input wire [6:0]in, output reg [12:0]out);

        always @ (*)begin
                casex (in)
                    7'bxxxxxx0: out <= 13'b1000000001000;
                    7'b00001x1: out <= 13'b0100000001000;
                    7'b00000x1: out <= 13'b1000000001000;
                    7'b00011x1: out <= 13'b1000000001000;
                    7'b00010x1: out <= 13'b0100000001000;
                    7'b0010xx1: out <= 13'b0001001000010;
                    7'b0011xx1: out <= 13'b1001001000000;
                    7'b0100xx1: out <= 13'b0011010000010;
                    7'b0101xx1: out <= 13'b0011010000100;
                    7'b0110xx1: out <= 13'b1011010100000;
                    7'b0111xx1: out <= 13'b1000000111000;
                    7'b1000x11: out <= 13'b0100000001000;
                    7'b1000x01: out <= 13'b1000000001000;
                    7'b1001x11: out <= 13'b1000000001000;
                    7'b1001x01: out <= 13'b0100000001000;
                    7'b1010xx1: out <= 13'b0011011000010;
                    7'b1011xx1: out <= 13'b1011011100000;
                    7'b1100xx1: out <= 13'b0100000001000;
                    7'b1101xx1: out <= 13'b0000000001001;
                    7'b1110xx1: out <= 13'b0011100000010;
                    7'b1111xx1: out <= 13'b1011100100000;
                endcase
        end
endmodule

lab09dig/E5/E5_tb.v
//José Alejandro Rodríguez Porras 19131
//Electrónica Digital 1
//Laboratorio 9
//Ejercicio 5
//Memoria ROM testbench
module testbench();

reg [6:0]in;
wire [12:0]out;

ROM rom(in, out);

initial begin

    $display("in      | out");
    $monitor("%b|   %b   ", in, out);
    in = 7'b0000000;
    #1 in = 7'b0000000;
    //7'bxxxxxx0
    #1 in = 7'b0000010;
    #1 in = 7'b0000100;
    //7'b00001x1
    #1 in = 7'b0000101;
    #1 in = 7'b0000111;
    //7'b00000x1
    #1 in = 7'b0000001;
    #1 in = 7'b0000011;
    //7'b00011x1
    #1 in = 7'b0001101;
    #1 in = 7'b0001111;
    //7'b00010x1
    #1 in = 7'b0001011;
    #1 in = 7'b0001001;
    //7'b0010xx1
    #1 in = 7'b0010101;
    #1 in = 7'b0010011;
    //7'b0011xx1
    #1 in = 7'b0011001;
    #1 in = 7'b0011111;
    //7'b0100xx1
    #1 in = 7'b0100111;
    #1 in = 7'b0100011;
    //7'b0101xx1
    #1 in = 7'b0101101;
    #1 in = 7'b0101001;
    //7'b0110xx1
    #1 in = 7'b0110001;
    #1 in = 7'b0110111;
    //7'b0111xx1
    #1 in = 7'b0111101;
    #1 in = 7'b0111011;
    //7'b1000x11
    #1 in = 7'b1000111;
    #1 in = 7'b1000011;
    //7'b1000x01
    #1 in = 7'b1000001;
    #1 in = 7'b1000101;
    //7'b1001x11
    #1 in = 7'b1001011;
    #1 in = 7'b1001111;
    //7'b1001x01
    #1 in = 7'b1001101;
    #1 in = 7'b1001001;
    //7'b1010xx1
    #1 in = 7'b1010001;
    #1 in = 7'b1010111;
    //7'b1011xx1
    #1 in = 7'b1011111;
    #1 in = 7'b1011101;
    //7'b1100xx1
    #1 in = 7'b1100111;
    #1 in = 7'b1100001;
    //7'b1101xx1
    #1 in = 7'b1101001;
    #1 in = 7'b1101111;
    //7'b1110xx1
    #1 in = 7'b1110001;
    #1 in = 7'b1110111;
    //7'b1111xx1
    #1 in = 7'b1111011;
    #1 in = 7'b1111101;

end

initial
    #100 $finish;

initial begin
    $dumpfile("E5_tb.vcd");
    $dumpvars(0, testbench); 
end

endmodule

lab09dig/E5/E5_tb.vcd
$date
	Sat Oct 31 10:53:57 2020
$end
$version
	Icarus Verilog
$end
$timescale
	1ps
$end
$scope module testbench $end
$var wire 13 ! out [12:0] $end
$var reg 7 " in [6:0] $end
$scope module rom $end
$var wire 7 # in [6:0] $end
$var reg 13 $ out [12:0] $end
$upscope $end
$upscope $end
$enddefinitions $end
#0
$dumpvars
b1000000001000 $
b0 #
b0 "
b1000000001000 !
$end
#2
b10 "
b10 #
#3
b100 "
b100 #
#4
b100000001000 !
b100000001000 $
b101 "
b101 #
#5
b111 "
b111 #
#6
b1000000001000 !
b1000000001000 $
b1 "
b1 #
#7
b11 "
b11 #
#8
b1101 "
b1101 #
#9
b1111 "
b1111 #
#10
b100000001000 !
b100000001000 $
b1011 "
b1011 #
#11
b1001 "
b1001 #
#12
b1001000010 !
b1001000010 $
b10101 "
b10101 #
#13
b10011 "
b10011 #
#14
b1001001000000 !
b1001001000000 $
b11001 "
b11001 #
#15
b11111 "
b11111 #
#16
b11010000010 !
b11010000010 $
b100111 "
b100111 #
#17
b100011 "
b100011 #
#18
b11010000100 !
b11010000100 $
b101101 "
b101101 #
#19
b101001 "
b101001 #
#20
b1011010100000 !
b1011010100000 $
b110001 "
b110001 #
#21
b110111 "
b110111 #
#22
b1000000111000 !
b1000000111000 $
b111101 "
b111101 #
#23
b111011 "
b111011 #
#24
b100000001000 !
b100000001000 $
b1000111 "
b1000111 #
#25
b1000011 "
b1000011 #
#26
b1000000001000 !
b1000000001000 $
b1000001 "
b1000001 #
#27
b1000101 "
b1000101 #
#28
b1001011 "
b1001011 #
#29
b1001111 "
b1001111 #
#30
b100000001000 !
b100000001000 $
b1001101 "
b1001101 #
#31
b1001001 "
b1001001 #
#32
b11011000010 !
b11011000010 $
b1010001 "
b1010001 #
#33
b1010111 "
b1010111 #
#34
b1011011100000 !
b1011011100000 $
b1011111 "
b1011111 #
#35
b1011101 "
b1011101 #
#36
b100000001000 !
b100000001000 $
b1100111 "
b1100111 #
#37
b1100001 "
b1100001 #
#38
b1001 !
b1001 $
b1101001 "
b1101001 #
#39
b1101111 "
b1101111 #
#40
b11100000010 !
b11100000010 $
b1110001 "
b1110001 #
#41
b1110111 "
b1110111 #
#42
b1011100100000 !
b1011100100000 $
b1111011 "
b1111011 #
#43
b1111101 "
b1111101 #
