lab08dig/E2/E2.v
//José Alejandro Rodríguez Porras 19131
//Electrónica Digital 1
//Lab 8 Ejercicio 2
//Memoria ROM de 4k x 8
//input es la dirección de memoria en la que se guarda el valor
//output es el dato que se almacena en la dirección
module ROM(input wire [11:0]direccion, output wire [7:0]data);
reg [7:0] memoria[0:4095];
initial begin 
// readmemb lee el archivo lista y almacena sus datos en una variable
    $readmemb("lista.list", memoria);
end
//asignación del dato en la dirección de la memoria
assign data = memoria[direccion];
endmodule

lab08dig/E2/E2_tb.v
//José Alejandro Rodríguez Porras 19131
//Electrónica Digital 1
//Lab 8 Ejercicio 2 testbench
module testbench();
reg [11:0]direccion;
wire [7:0]data;

ROM rom(direccion, data);

initial begin
    $display("ROM");
    $display("direccion    | data");
    $monitor("%b | %b", direccion, data);
    //Simulación en la que se muestran cada una de las localidades de memoria (algunas con datos dentro de ellas y algunas sin datos guardados en ella)
       direccion = 12'd0;
    #1 direccion = 12'd1;
    #1 direccion = 12'd2;
    #1 direccion = 12'd3;
    #1 direccion = 12'd4;
    #1 direccion = 12'd5;
    #1 direccion = 12'd6;
    #1 direccion = 12'd7;
    #1 direccion = 12'd8;
    #1 direccion = 12'd9;
    #1 direccion = 12'd10;
    #1 direccion = 12'd11;
    #1 direccion = 12'd12;
    #1 direccion = 12'd13;
end
//final de la simulación
initial
    #20 $finish;
//Creación del vcd
initial begin 
    $dumpfile("E2_tb.vcd");
    $dumpvars(0, testbench);
end
endmodule

lab08dig/E2/E2_tb.vcd
$date
	Sat Oct 24 22:29:37 2020
$end
$version
	Icarus Verilog
$end
$timescale
	1ps
$end
$scope module testbench $end
$var wire 8 ! data [7:0] $end
$var reg 12 " direccion [11:0] $end
$scope module rom $end
$var wire 8 # data [7:0] $end
$var wire 12 $ direccion [11:0] $end
$upscope $end
$upscope $end
$enddefinitions $end
#0
$dumpvars
b0 $
b1 #
b0 "
b1 !
$end
#1
b10 !
b10 #
b1 "
b1 $
#2
bx !
bx #
b10 "
b10 $
#3
b11 "
b11 $
#4
b100 "
b100 $
#5
b100 !
b100 #
b101 "
b101 $
#6
b1000 !
b1000 #
b110 "
b110 $
#7
b10000 !
b10000 #
b111 "
b111 $
#8
b100000 !
b100000 #
b1000 "
b1000 $
#9
b1000000 !
b1000000 #
b1001 "
b1001 $
#10
b10000000 !
b10000000 #
b1010 "
b1010 $
#11
b10000001 !
b10000001 #
b1011 "
b1011 $
#12
b1000010 !
b1000010 #
b1100 "
b1100 $
#13
bx !
bx #
b1101 "
b1101 $
