lab08dig/E1/E1.v
//José Alejandro Rodríguez Porras 19131
//Electrónica Digital 1
//Lab 8 Ejercicio 1
//Contador de 12 bits, con Load, Enabled y Reset
module up_counter(input clk, rst, Load, Enabled, input [11:0]Loadvalue, output [11:0]counter);
reg [11:0] counter_up;
// Load y reset asíncronos
always @(posedge clk or posedge Load or posedge rst)
// El reset pone todos los bits del contador en 0 de forma asíncrona
begin
if (rst)
    counter_up <= 12'b000000000000;
// El Load asigna un valor específico(Loadvalue) al contador mientras Load sea igual a 1
else if(Load)
    counter_up <= Loadvalue;
//Mientras Enable sea igual a 1 el contador va sumando uno al valor previo, "va contando"
else begin 
//Si el contador llega a su valor máximo, es decir 4095 el siguiente valor que se le asigna es 0
if (Enabled == 1 & counter_up == 12'b111111111111)
    counter_up = 12'd0;
//El contador cuenta
else if (Enabled == 1)
    counter_up <= counter_up + 12'd1;
end    
end
//Se asigna el valor del contador a la salida
assign counter = counter_up;
endmodule

lab08dig/E1/E1_tb.v
//José Alejandro Rodríguez Porras 
//Electrónica Digital 1
//Lab 8 Ejercicio 1 testbench
module testbench();
reg clk, rst, Load, Enabled;
reg [11:0]Loadvalue;
wire [11:0]counter;

up_counter count(clk, rst, Load, Enabled, Loadvalue, counter);
initial begin 
forever #5 clk=~clk;
end
initial begin
$display("Load Enabled Loadvalue | counter ");
$display("-----------------------|---------");
$monitor("%d      %d      %d     | %d", Load, Enabled, Loadvalue, counter);
//Valores iniciales de los inputs, el clock y el rst
clk=0; rst = 0; Load = 0;  Enabled = 0; Loadvalue = 12'b000000000000; 
//Prueba de que el contador no cuenta si el Enabled es 0
#1  rst = 1;
#1  rst = 0; 
//Prueba de que el contador comienza a contar cuanto se el Enabled es 1
#40  Enabled = 1;
//Prueba de una carga de un valor al contador de forma asíncrona cuando el Load es 1
#100 Load = 1; Loadvalue = 12'b000000011010;
//La salida del contador es el valor cargado por el Load mientras el Load se quede en 1
// Cuando el Load es 0 el contador comienza a contar desde el valor asignado cuando se activó el Load
#100 Load = 0; 
//Prueba de que el contador deja de contar cuando el Enabled es 0.
#100 Enabled = 0;
// Se carga el valor de 4094 con el Load al contador
#100 Enabled = 1; Loadvalue = 12'b111111111110; 
#60 Load = 1; 
//Prueba de que el contador vuelve todos sus bits a 0 luego de llegar a su valor máximo (4095) 
#10  Load = 0;
//Prueba del reset asíncrono
#100 rst = 1;
#1   rst = 0;
//final de la simulación
#40 $finish;
end
//creación del archivo vcd  (diagrama de timing)
initial begin
        $dumpfile("E1_tb.vcd");
        $dumpvars(0,testbench);
    end
endmodule

lab08dig/E1/E1_tb.vcd
$date
	Sat Oct 24 22:14:19 2020
$end
$version
	Icarus Verilog
$end
$timescale
	1ps
$end
$scope module testbench $end
$var wire 12 ! counter [11:0] $end
$var reg 1 " Enabled $end
$var reg 1 # Load $end
$var reg 12 $ Loadvalue [11:0] $end
$var reg 1 % clk $end
$var reg 1 & rst $end
$scope module count $end
$var wire 1 " Enabled $end
$var wire 1 # Load $end
$var wire 12 ' Loadvalue [11:0] $end
$var wire 1 % clk $end
$var wire 12 ( counter [11:0] $end
$var wire 1 & rst $end
$var reg 12 ) counter_up [11:0] $end
$upscope $end
$upscope $end
$enddefinitions $end
#0
$dumpvars
bx )
bx (
b0 '
0&
0%
b0 $
0#
0"
bx !
$end
#1
b0 !
b0 (
b0 )
1&
#2
0&
#5
1%
#10
0%
#15
1%
#20
0%
#25
1%
#30
0%
#35
1%
#40
0%
#42
1"
#45
b1 !
b1 (
b1 )
1%
#50
0%
#55
b10 !
b10 (
b10 )
1%
#60
0%
#65
b11 !
b11 (
b11 )
1%
#70
0%
#75
b100 !
b100 (
b100 )
1%
#80
0%
#85
b101 !
b101 (
b101 )
1%
#90
0%
#95
b110 !
b110 (
b110 )
1%
#100
0%
#105
b111 !
b111 (
b111 )
1%
#110
0%
#115
b1000 !
b1000 (
b1000 )
1%
#120
0%
#125
b1001 !
b1001 (
b1001 )
1%
#130
0%
#135
b1010 !
b1010 (
b1010 )
1%
#140
0%
#142
b11010 !
b11010 (
b11010 )
b11010 $
b11010 '
1#
#145
1%
#150
0%
#155
1%
#160
0%
#165
1%
#170
0%
#175
1%
#180
0%
#185
1%
#190
0%
#195
1%
#200
0%
#205
1%
#210
0%
#215
1%
#220
0%
#225
1%
#230
0%
#235
1%
#240
0%
#242
0#
#245
b11011 !
b11011 (
b11011 )
1%
#250
0%
#255
b11100 !
b11100 (
b11100 )
1%
#260
0%
#265
b11101 !
b11101 (
b11101 )
1%
#270
0%
#275
b11110 !
b11110 (
b11110 )
1%
#280
0%
#285
b11111 !
b11111 (
b11111 )
1%
#290
0%
#295
b100000 !
b100000 (
b100000 )
1%
#300
0%
#305
b100001 !
b100001 (
b100001 )
1%
#310
0%
#315
b100010 !
b100010 (
b100010 )
1%
#320
0%
#325
b100011 !
b100011 (
b100011 )
1%
#330
0%
#335
b100100 !
b100100 (
b100100 )
1%
#340
0%
#342
0"
#345
1%
#350
0%
#355
1%
#360
0%
#365
1%
#370
0%
#375
1%
#380
0%
#385
1%
#390
0%
#395
1%
#400
0%
#405
1%
#410
0%
#415
1%
#420
0%
#425
1%
#430
0%
#435
1%
#440
0%
#442
b111111111110 $
b111111111110 '
1"
#445
b100101 !
b100101 (
b100101 )
1%
#450
0%
#455
b100110 !
b100110 (
b100110 )
1%
#460
0%
#465
b100111 !
b100111 (
b100111 )
1%
#470
0%
#475
b101000 !
b101000 (
b101000 )
1%
#480
0%
#485
b101001 !
b101001 (
b101001 )
1%
#490
0%
#495
b101010 !
b101010 (
b101010 )
1%
#500
0%
#502
b111111111110 !
b111111111110 (
b111111111110 )
1#
#505
1%
#510
0%
#512
0#
#515
b111111111111 !
b111111111111 (
b111111111111 )
1%
#520
0%
#525
b0 !
b0 (
b0 )
1%
#530
0%
#535
b1 !
b1 (
b1 )
1%
#540
0%
#545
b10 !
b10 (
b10 )
1%
#550
0%
#555
b11 !
b11 (
b11 )
1%
#560
0%
#565
b100 !
b100 (
b100 )
1%
#570
0%
#575
b101 !
b101 (
b101 )
1%
#580
0%
#585
b110 !
b110 (
b110 )
1%
#590
0%
#595
b111 !
b111 (
b111 )
1%
#600
0%
#605
b1000 !
b1000 (
b1000 )
1%
#610
0%
#612
b0 !
b0 (
b0 )
1&
#613
0&
#615
b1 !
b1 (
b1 )
1%
#620
0%
#625
b10 !
b10 (
b10 )
1%
#630
0%
#635
b11 !
b11 (
b11 )
1%
#640
0%
#645
b100 !
b100 (
b100 )
1%
