lab09dig/E1/E1.v
//José Alejandro Rodríguez Porras 19131
//Electrónica Digital 1
//Laboratorio 9
//Ejercicio 1
//Flip Flop tipo D de 1 bit con Enable
module FFD1(input clk, rst, enable, d, output reg q);
    always @ (posedge clk or posedge rst) begin
        if (rst)
            q <= 0;
        else if (enable)
            q <= d;
    end 
endmodule
//Flip Flop tipo D de 2 bits con Enable
module FFD2(input clk, rst, enable, input [1:0]d, output [1:0]q);
    
    FFD1 df1_1(clk, rst, enable, d[1], q[1]);
    FFD1 df1_0(clk, rst, enable, d[0], q[0]);

endmodule
//Flip Flop tipo D de 4 bits con Enable
module FFD4(input clk, rst, enable, input [3:0]d, output [3:0]q);
    
    FFD2 df2_1(clk, rst, enable, d[3:2], q[3:2]);
    FFD2 df2_0(clk, rst, enable, d[1:0], q[1:0]);

endmodule

lab09dig/E1/E1_tb.v
//José Alejandro Rodríguez Porras 19131
//Electrónica Digital 1
//Laboratorio 9
//Ejercicio 1 Testbench
//Flip Flop tipo D de 1 bit con Enable, Flip Flop tipo D de 2 bit con Enable, Flip Flop tipo D de 4 bit con Enable,
module testbench();
//Declaración de variables
    reg clk, rst, enable;
    reg [3:0]d;
    wire [3:0]q;
//Asignación de módulos
    FFD4 ffd4(clk, rst, enable, d, q);

//Prueba de funcionamiento del Flip Flop Tipo D con Enable de 1 bit
initial begin
    $display("rst enable d | q");
    $display("-------------|--");
    $monitor("%b    %b   %b| %b", rst, enable, d, q);
    clk = 0; rst = 0; enable = 0; d = 4'b0000;
    //Prueba de reset
    #1  rst = 1; enable = 0; d = 4'b0000;
    #1  rst = 0; enable = 0; d = 4'b0000;
    //Prueba de que cuando enable esta apagado q no se actualiza 
    #1  rst = 0; enable = 0; d = 4'b1001;
    #5  rst = 0; enable = 0; d = 4'b0000;
    //Prueba de que cuando enable esta encendido q se actualiza con los flancos positivos del clk
    #5  rst = 0; enable = 1; d = 4'b0101;
    #10 rst = 0; enable = 1; d = 4'b0000;
    //Prueba de que cuando enable esta apagado q no se actualiza 
    #10 rst = 0; enable = 0; d = 4'b0111;
    #10 rst = 0; enable = 0; d = 4'b0000;
    //Prueba de reset
    #10 rst = 0; enable = 1; d = 4'b1111;
    #10 rst = 1; enable = 1; d = 4'b0000;
    #1  rst = 0;
    #80 $finish;
end
always
        #5 clk = ~clk;
    initial begin
        $dumpfile("E1_tb.vcd");
        $dumpvars(0,testbench);
    end
endmodule

lab09dig/E1/E1_tb.vcd
$date
	Thu Oct 29 23:13:16 2020
$end
$version
	Icarus Verilog
$end
$timescale
	1ps
$end
$scope module testbench $end
$var wire 4 ! q [3:0] $end
$var reg 1 " clk $end
$var reg 4 # d [3:0] $end
$var reg 1 $ enable $end
$var reg 1 % rst $end
$scope module ffd4 $end
$var wire 1 " clk $end
$var wire 4 & d [3:0] $end
$var wire 1 $ enable $end
$var wire 1 % rst $end
$var wire 4 ' q [3:0] $end
$scope module df2_0 $end
$var wire 1 " clk $end
$var wire 2 ( d [1:0] $end
$var wire 1 $ enable $end
$var wire 1 % rst $end
$var wire 2 ) q [1:0] $end
$scope module df1_0 $end
$var wire 1 " clk $end
$var wire 1 * d $end
$var wire 1 $ enable $end
$var wire 1 % rst $end
$var reg 1 + q $end
$upscope $end
$scope module df1_1 $end
$var wire 1 " clk $end
$var wire 1 , d $end
$var wire 1 $ enable $end
$var wire 1 % rst $end
$var reg 1 - q $end
$upscope $end
$upscope $end
$scope module df2_1 $end
$var wire 1 " clk $end
$var wire 2 . d [1:0] $end
$var wire 1 $ enable $end
$var wire 1 % rst $end
$var wire 2 / q [1:0] $end
$scope module df1_0 $end
$var wire 1 " clk $end
$var wire 1 0 d $end
$var wire 1 $ enable $end
$var wire 1 % rst $end
$var reg 1 1 q $end
$upscope $end
$scope module df1_1 $end
$var wire 1 " clk $end
$var wire 1 2 d $end
$var wire 1 $ enable $end
$var wire 1 % rst $end
$var reg 1 3 q $end
$upscope $end
$upscope $end
$upscope $end
$upscope $end
$enddefinitions $end
#0
$dumpvars
x3
02
x1
00
bx /
b0 .
x-
0,
x+
0*
bx )
b0 (
bx '
b0 &
0%
0$
b0 #
0"
bx !
$end
#1
03
b0 /
01
0-
b0 !
b0 '
b0 )
0+
1%
#2
0%
#3
12
1*
b10 .
b1 (
b1001 #
b1001 &
#5
1"
#8
02
0*
b0 .
b0 (
b0 #
b0 &
#10
0"
#13
10
1*
b1 .
b1 (
b101 #
b101 &
1$
#15
b1 /
11
b101 !
b101 '
b1 )
1+
1"
#20
0"
#23
00
0*
b0 .
b0 (
b0 #
b0 &
#25
b0 )
0+
b0 !
b0 '
b0 /
01
1"
#30
0"
#33
10
1,
1*
b1 .
b11 (
b111 #
b111 &
0$
#35
1"
#40
0"
#43
00
0,
0*
b0 .
b0 (
b0 #
b0 &
#45
1"
#50
0"
#53
12
10
1,
1*
b11 .
b11 (
b1111 #
b1111 &
1$
#55
13
b11 /
11
1-
b1111 !
b1111 '
b11 )
1+
1"
#60
0"
#63
0+
b0 )
0-
01
b0 !
b0 '
b0 /
03
02
00
0,
0*
b0 .
b0 (
b0 #
b0 &
1%
#64
0%
