lab10dig/E1/E1.v
//José Alejandro Rodríguez Porras 19131
//Electrónica Digital 1
//Lab 10 Ejercicio 1
//Módulo con Program Counter, ROM de 4096x8 y Fetch
//Contador de 12 bits, con Load, Enabled y Reset
module up_counter(input clk, rst, Load, Enabled, input [11:0]Loadvalue, output [11:0]counter);
    reg [11:0] counter_up;
    // Load y reset asíncronos
    always @(posedge clk or posedge Load or posedge rst)
    // El reset pone todos los bits del contador en 0 de forma asíncrona
        begin
            if (rst)
                counter_up <= 12'b000000000000;
            // El Load asigna un valor específico(Loadvalue) al contador mientras Load sea igual a 1
            else if(Load)
                counter_up <= Loadvalue;
            //Mientras Enable sea igual a 1 el contador va sumando uno al valor previo, "va contando"
            else begin 
            //Si el contador llega a su valor máximo, es decir 4095 el siguiente valor que se le asigna es 0
                if (Enabled == 1 & counter_up == 12'b111111111111)
                    counter_up = 12'd0;
                //El contador cuenta
                else if (Enabled == 1)
                    counter_up <= counter_up + 12'd1;
            end    
    end
    //Se asigna el valor del contador a la salida
    assign counter = counter_up;
endmodule

//Memoria ROM de 4k x 8
//input es la dirección de memoria en la que se guarda el valor
//output es el dato que se almacena en la dirección
module ROM(input wire [11:0]direccion, output wire [7:0]data);
    reg [7:0] memoria[0:4095];
    initial begin 
    // readmemb lee el archivo lista y almacena sus datos en una variable
        $readmemb("lista.list", memoria);
    end
    //asignación del dato en la dirección de la memoria
    assign data = memoria[direccion];
endmodule

//Fetch (Flip flop D de 8 bits de entrada y 2 salidas de 4 bits)
module fetch(input clk, rst, enable, input [7:0]d, output reg [3:0]instr, output reg [3:0]oprnd);
    always @ (posedge clk or posedge rst) begin
        if (rst) begin
            instr <= 4'b0000;
            oprnd <= 4'b0000;
        end
        else if (enable) begin
            instr <= d[7:4];
            oprnd <= d[3:0];
        end
    end
endmodule

//Módulo con Program Counter de 12 bits, ROM de 4096x8 y Fetch de 8 bits
module count_rom_fetch(input rst, clk, enabled, load, input [11:0]loadvalue, output wire [7:0]program_byte, output wire [3:0]instr, output wire [3:0] oprnd);
    wire [11:0]counter;
    up_counter upcounter(clk, rst, load, enabled, loadvalue, counter);
    ROM rom(counter, program_byte);
    fetch FETCH(clk, rst, enabled, program_byte, instr, oprnd);
endmodule

lab10dig/E1/E1_tb.v
//José Alejandro Rodríguez Porras 19131
//Electrónica Digital 1
//Lab 10 Ejercicio 1 Testbench
//Módulo con Program Counter, ROM de 4096x8 y Fetch
module testbench();
    //Declaración de variables
    reg clk, rst, enabled, load;
    reg [11:0]loadvalue;
    wire [7:0]program_byte;
    wire [3:0]instr;
    wire [3:0]oprnd;
    //Asignación de módulos
    count_rom_fetch COUNT_ROM_FETCHU(rst, clk, enabled, load, loadvalue, program_byte, instr, oprnd);
    //Prueba de funcionamiento del Módulo con counter, rom y fecth
    initial begin 
        $display("rst enabled load loadvalue    | program_byte   instr oprnd");
        $display("------------------------------|---------------------------");
        $monitor("%b      %b     %b   %b| %b         %b     %b", rst, enabled, load, loadvalue, program_byte, instr, oprnd);
        clk = 0; rst = 0; enabled = 0; load = 0; loadvalue = 12'b000000000000;
        //Prueba del reset
        #1   rst = 1; enabled = 0; load = 0; loadvalue = 12'b000000000000;
        #1   rst = 0; enabled = 1; load = 0; loadvalue = 12'b000000000000;
        //Prueba del enable en 0
        #20  rst = 0; enabled = 0; load = 0; loadvalue = 12'b000000000000;
        #20  rst = 0; enabled = 0; load = 0; loadvalue = 12'b000000000000;
        //Prueba del enable en 1, comienza a contar, y loadvalue no se carga si load es 0
        #20  rst = 0; enabled = 1; load = 0; loadvalue = 12'b000000001000;
        //Prueba de la carga de un valor loadvalue con load igual a 1
        #30  rst = 0; enabled = 1; load = 1; loadvalue = 12'b000000001000;
        //Prueba de que comienza a contar desde la dirección que se cargó
        #30  rst = 0; enabled = 1; load = 0; loadvalue = 12'b000000001000;
        //Prueba del reset
        #20  rst = 1; enabled = 0; load = 0; loadvalue = 12'b000001100110;
        #1   rst = 0; enabled = 0; load = 0; loadvalue = 12'b000001100110;
        //Prueba de la carga de un valor de una dirección de la ROM que no tiene ningún valor guardado
        #1   rst = 0; enabled = 1; load = 1; loadvalue = 12'b000001100110;
        #1   rst = 0; enabled = 1; load = 0; loadvalue = 12'b000001100110;
        //Prueba de la carga de un valor cualquiera de una dirección de la ROM que si tiene un valor guardado
        #1   rst = 0; enabled = 1; load = 1; loadvalue = 12'b000000000001;
        #1   rst = 0; enabled = 1; load = 0; loadvalue = 12'b000000000001;
    end
    //Fin de la simulación
    initial 
    #200 $finish;
    //Clock
    always
        #5 clk = ~clk;
    //Creación del diagrama de timing
    initial begin
        $dumpfile("E1_tb.vcd");
        $dumpvars(0,testbench);
    end
endmodule

lab10dig/E1/E1_tb.vcd
$date
	Sat Nov 07 21:01:04 2020
$end
$version
	Icarus Verilog
$end
$timescale
	1ps
$end
$scope module testbench $end
$var wire 8 ! program_byte [7:0] $end
$var wire 4 " oprnd [3:0] $end
$var wire 4 # instr [3:0] $end
$var reg 1 $ clk $end
$var reg 1 % enabled $end
$var reg 1 & load $end
$var reg 12 ' loadvalue [11:0] $end
$var reg 1 ( rst $end
$scope module COUNT_ROM_FETCHU $end
$var wire 1 $ clk $end
$var wire 1 % enabled $end
$var wire 1 & load $end
$var wire 12 ) loadvalue [11:0] $end
$var wire 1 ( rst $end
$var wire 8 * program_byte [7:0] $end
$var wire 4 + oprnd [3:0] $end
$var wire 4 , instr [3:0] $end
$var wire 12 - counter [11:0] $end
$scope module FETCH $end
$var wire 1 $ clk $end
$var wire 1 % enable $end
$var wire 1 ( rst $end
$var wire 8 . d [7:0] $end
$var reg 4 / instr [3:0] $end
$var reg 4 0 oprnd [3:0] $end
$upscope $end
$scope module rom $end
$var wire 8 1 data [7:0] $end
$var wire 12 2 direccion [11:0] $end
$upscope $end
$scope module upcounter $end
$var wire 1 % Enabled $end
$var wire 1 & Load $end
$var wire 12 3 Loadvalue [11:0] $end
$var wire 1 $ clk $end
$var wire 1 ( rst $end
$var wire 12 4 counter [11:0] $end
$var reg 12 5 counter_up [11:0] $end
$upscope $end
$upscope $end
$upscope $end
$enddefinitions $end
#0
$dumpvars
bx 5
bx 4
b0 3
bx 2
bx 1
bx 0
bx /
bx .
bx -
bx ,
bx +
bx *
b0 )
0(
b0 '
0&
0%
0$
bx #
bx "
bx !
$end
#1
b0 "
b0 +
b0 0
b0 #
b0 ,
b0 /
b1 !
b1 *
b1 .
b1 1
b0 -
b0 2
b0 4
b0 5
1(
#2
1%
0(
#5
b1 "
b1 +
b1 0
b10 !
b10 *
b10 .
b10 1
b1 -
b1 2
b1 4
b1 5
1$
#10
0$
#15
b10 "
b10 +
b10 0
b100 !
b100 *
b100 .
b100 1
b10 -
b10 2
b10 4
b10 5
1$
#20
0$
#22
0%
#25
1$
#30
0$
#35
1$
#40
0$
#45
1$
#50
0$
#55
1$
#60
0$
#62
b1000 '
b1000 )
b1000 3
1%
#65
b100 "
b100 +
b100 0
b1000 !
b1000 *
b1000 .
b1000 1
b11 -
b11 2
b11 4
b11 5
1$
#70
0$
#75
b1000 "
b1000 +
b1000 0
b10000 !
b10000 *
b10000 .
b10000 1
b100 -
b100 2
b100 4
b100 5
1$
#80
0$
#85
b0 "
b0 +
b0 0
b1 #
b1 ,
b1 /
b100000 !
b100000 *
b100000 .
b100000 1
b101 -
b101 2
b101 4
b101 5
1$
#90
0$
#92
b10000001 !
b10000001 *
b10000001 .
b10000001 1
b1000 -
b1000 2
b1000 4
b1000 5
1&
#95
b1 "
b1 +
b1 0
b1000 #
b1000 ,
b1000 /
1$
#100
0$
#105
1$
#110
0$
#115
1$
#120
0$
#122
0&
#125
b1000010 !
b1000010 *
b1000010 .
b1000010 1
b1001 -
b1001 2
b1001 4
b1001 5
1$
#130
0$
#135
b10 "
b10 +
b10 0
b100 #
b100 ,
b100 /
bx !
bx *
bx .
bx 1
b1010 -
b1010 2
b1010 4
b1010 5
1$
#140
0$
#142
b0 "
b0 +
b0 0
b0 #
b0 ,
b0 /
b1 !
b1 *
b1 .
b1 1
b0 -
b0 2
b0 4
b0 5
b1100110 '
b1100110 )
b1100110 3
0%
1(
#143
0(
#144
bx !
bx *
bx .
bx 1
b1100110 -
b1100110 2
b1100110 4
b1100110 5
1&
1%
#145
bx "
bx +
bx 0
bx #
bx ,
bx /
b1100111 -
b1100111 2
b1100111 4
b1100111 5
0&
1$
#146
b10 !
b10 *
b10 .
b10 1
b1 -
b1 2
b1 4
b1 5
b1 '
b1 )
b1 3
1&
#147
0&
#150
0$
#155
b10 "
b10 +
b10 0
b0 #
b0 ,
b0 /
b100 !
b100 *
b100 .
b100 1
b10 -
b10 2
b10 4
b10 5
1$
#160
0$
#165
b100 "
b100 +
b100 0
b1000 !
b1000 *
b1000 .
b1000 1
b11 -
b11 2
b11 4
b11 5
1$
#170
0$
#175
b1000 "
b1000 +
b1000 0
b10000 !
b10000 *
b10000 .
b10000 1
b100 -
b100 2
b100 4
b100 5
1$
#180
0$
#185
b0 "
b0 +
b0 0
b1 #
b1 ,
b1 /
b100000 !
b100000 *
b100000 .
b100000 1
b101 -
b101 2
b101 4
b101 5
1$
#190
0$
#195
b10 #
b10 ,
b10 /
b1000000 !
b1000000 *
b1000000 .
b1000000 1
b110 -
b110 2
b110 4
b110 5
1$
