lab03dig/t02sop/t02sop.v
//Alejandro Rodríguez 19131
//Lab 3 t2 sop
module gates(); //creación de módulo
//variables
reg A,B,C; //in variables
wire w1,w2,w3; //or out variables
wire n1,n2,n3; //not out variables
wire a1; //and out variable
not PnA(n1,A); //not gates para A, B y C
not PnB(n2,B);
not PnC(n3,C);
and Pw1(w1,n1,n2,C);//A'B'C
and Pw2(w2,A,B,n3);//ABC'
and Pw3(w3,A,B,C);//ABC
or Pa1(a1,w1,w2,w3);//Y2
//comienzo
initial begin
    $display("A B C | Y");
    $display("---------");
    $monitor("%b %b %b | %b", A, B, C, a1);
    //condición inicial
    A = 0; B = 0; C = 0;
    //simulación combinaciones
    #1 C = 1;
    #1 B = 1; C = 0;
    #1 C = 1;
    #1 A = 1; B = 0; C = 0;
    #1 C = 1;
    #1 B = 1; C = 0;
    #1 C = 1;
    #1 $finish; //final de la simulación
end
initial
    begin
        $dumpfile("t02sop_tb.vcd"); //se crea archivo vcd
        $dumpvars(0,gates);
    end
endmodule //fin del módulo

lab03dig/t02sop/t02sop_tb.vcd
$date
	Fri Jul 31 23:27:49 2020
$end
$version
	Icarus Verilog
$end
$timescale
	1ps
$end
$scope module gates $end
$var wire 1 ! a1 $end
$var wire 1 " n1 $end
$var wire 1 # n2 $end
$var wire 1 $ n3 $end
$var wire 1 % w1 $end
$var wire 1 & w2 $end
$var wire 1 ' w3 $end
$var reg 1 ( A $end
$var reg 1 ) B $end
$var reg 1 * C $end
$upscope $end
$enddefinitions $end
#0
$dumpvars
0*
0)
0(
0'
0&
0%
1$
1#
1"
0!
$end
#1
1!
1%
0$
1*
#2
0!
0%
1$
0#
0*
1)
#3
0$
1*
#4
1$
1#
0"
0*
0)
1(
#5
0$
1*
#6
1!
1&
1$
0#
0*
1)
#7
0&
1'
0$
1*
