lab08dig/E3/E3.v
//José Alejandro Rodríguez Porras 19131
//Electrónica Digital 1
//Lab 8 Ejercicio 3 
//ALU
module ALU(input wire [3:0]A, input wire [3:0]B, input wire [2:0]opcode, output reg [3:0]Y);
    always @(opcode or A or B) begin 
        //case para elegir cada uno de los modos de operación
        case(opcode)
        3'b000: Y <= A & B; //A AND B
        3'b001: Y <= A | B; // A OR B
        3'b010: Y <= A + B; // A + B
        3'b011: Y <= 4'b0000; // Sin uso
        3'b100: Y <= A & ~B; //A AND B'
        3'b101: Y <= A | ~B; //A OR B'
        3'b110: Y <= A - B; //A - B
        3'b111: Y <= (A < B) ? 1:0; // Y es 1 solo cuando A es menor que B
        //valor por defecto de salida
        default: Y <= 4'b0000;
        endcase
    end
endmodule

lab08dig/E3/E3_tb.v
//José ALejandro Rodríguez Porras 19131
//Electrónica Digital 1
//Lab 8 Ejercicio 3 testbench
module testbench();
    reg [3:0]A;
    reg [3:0]B;
    reg [2:0]opcode;
    wire [3:0]Y;

ALU alu(A, B, opcode, Y);
//Comienzo de la simulación
initial begin
   #1 $display("A        B    opcode |    Y");
      $display("---------------------|-----------");
    $monitor("%b    %b    %b  |   %b", A, B, opcode, Y);
// Prueba A AND B
    A = 4'b0000; B = 4'b0000; opcode = 3'b000; 
   #1 A = 4'b0001; B = 4'b0000; opcode = 3'b000;
   #1 A = 4'b0000; B = 4'b0001; opcode = 3'b000;
   #1 A = 4'b0001; B = 4'b0001; opcode = 3'b000;
   #1 A = 4'b0110; B = 4'b0110; opcode = 3'b000;
   #1 A = 4'b0011; B = 4'b0010; opcode = 3'b000;
//Prueba A OR B
   #1 A = 4'b0000; B = 4'b0000; opcode = 3'b001;
   #1 A = 4'b0000; B = 4'b0001; opcode = 3'b001;
   #1 A = 4'b0001; B = 4'b0000; opcode = 3'b001;
   #1 A = 4'b1010; B = 4'b0010; opcode = 3'b001;
//Prueba A + B
   #1 A = 4'b0000; B = 4'b0000; opcode = 3'b010;//0+0 = 0
   #1 A = 4'b1000; B = 4'b0011; opcode = 3'b010;//8+3 = 11
   #1 A = 4'b0000; B = 4'b0001; opcode = 3'b010;//0+1 = 1
   #1 A = 4'b0001; B = 4'b0010; opcode = 3'b010;//1+2 = 3
   #1 A = 4'b0001; B = 4'b0101; opcode = 3'b010;//1+5 = 6
//Prueba sin uso (salida es 0 siempre)
   #1 A = 4'b0000; B = 4'b0000; opcode = 3'b011;
   #1 A = 4'b0001; B = 4'b0110; opcode = 3'b011;
//Prueba A AND B'
   #1 A = 4'b0000; B = 4'b0000; opcode = 3'b100;
   #1 A = 4'b0001; B = 4'b0000; opcode = 3'b100;
   #1 A = 4'b0011; B = 4'b0001; opcode = 3'b100;
   #1 A = 4'b0100; B = 4'b0010; opcode = 3'b100;
//Prueba A OR B' 
   #1 A = 4'b0000; B = 4'b0000; opcode = 3'b101;
   #1 A = 4'b0000; B = 4'b0001; opcode = 3'b101;
   #1 A = 4'b0010; B = 4'b0000; opcode = 3'b101;
//Prueba A - B
   #1 A = 4'b0000; B = 4'b0000; opcode = 3'b110;// 0 - 0 = 0
   #1 A = 4'b0001; B = 4'b0000; opcode = 3'b110;// 1-0 = 1
   #1 A = 4'b0010; B = 4'b0010; opcode = 3'b110;//2-2 = 0
   #1 A = 4'b0100; B = 4'b0001; opcode = 3'b110;//4-1 = 3
//Prueba Y = 1 solo cuando A<B
   #1 A = 4'b0011; B = 4'b0011; opcode = 3'b111;
   #1 A = 4'b0110; B = 4'b0111; opcode = 3'b111;
   #1 A = 4'b0100; B = 4'b0010; opcode = 3'b111;
   #1 A = 4'b0101; B = 4'b0010; opcode = 3'b111;
end    
//final de la simulación
initial
    #40 $finish;
//Creación del vcd
initial begin 
    $dumpfile("E3_tb.vcd");
    $dumpvars(0, testbench);
end
endmodule

lab08dig/E3/E3_tb.vcd
$date
	Sat Oct 24 22:49:32 2020
$end
$version
	Icarus Verilog
$end
$timescale
	1ps
$end
$scope module testbench $end
$var wire 4 ! Y [3:0] $end
$var reg 4 " A [3:0] $end
$var reg 4 # B [3:0] $end
$var reg 3 $ opcode [2:0] $end
$scope module alu $end
$var wire 4 % A [3:0] $end
$var wire 4 & B [3:0] $end
$var wire 3 ' opcode [2:0] $end
$var reg 4 ( Y [3:0] $end
$upscope $end
$upscope $end
$enddefinitions $end
#0
$dumpvars
bx (
bx '
bx &
bx %
bx $
bx #
bx "
bx !
$end
#1
b0 !
b0 (
b0 $
b0 '
b0 #
b0 &
b0 "
b0 %
#2
b1 "
b1 %
#3
b1 #
b1 &
b0 "
b0 %
#4
b1 !
b1 (
b1 "
b1 %
#5
b110 !
b110 (
b110 #
b110 &
b110 "
b110 %
#6
b10 !
b10 (
b10 #
b10 &
b11 "
b11 %
#7
b0 !
b0 (
b1 $
b1 '
b0 #
b0 &
b0 "
b0 %
#8
b1 !
b1 (
b1 #
b1 &
#9
b0 #
b0 &
b1 "
b1 %
#10
b1010 !
b1010 (
b10 #
b10 &
b1010 "
b1010 %
#11
b0 !
b0 (
b10 $
b10 '
b0 #
b0 &
b0 "
b0 %
#12
b1011 !
b1011 (
b11 #
b11 &
b1000 "
b1000 %
#13
b1 !
b1 (
b1 #
b1 &
b0 "
b0 %
#14
b11 !
b11 (
b10 #
b10 &
b1 "
b1 %
#15
b110 !
b110 (
b101 #
b101 &
#16
b0 !
b0 (
b11 $
b11 '
b0 #
b0 &
b0 "
b0 %
#17
b110 #
b110 &
b1 "
b1 %
#18
b100 $
b100 '
b0 #
b0 &
b0 "
b0 %
#19
b1 !
b1 (
b1 "
b1 %
#20
b10 !
b10 (
b1 #
b1 &
b11 "
b11 %
#21
b100 !
b100 (
b10 #
b10 &
b100 "
b100 %
#22
b1111 !
b1111 (
b101 $
b101 '
b0 #
b0 &
b0 "
b0 %
#23
b1110 !
b1110 (
b1 #
b1 &
#24
b1111 !
b1111 (
b0 #
b0 &
b10 "
b10 %
#25
b0 !
b0 (
b110 $
b110 '
b0 "
b0 %
#26
b1 !
b1 (
b1 "
b1 %
#27
b0 !
b0 (
b10 #
b10 &
b10 "
b10 %
#28
b11 !
b11 (
b1 #
b1 &
b100 "
b100 %
#29
b0 !
b0 (
b111 $
b111 '
b11 #
b11 &
b11 "
b11 %
#30
b1 !
b1 (
b111 #
b111 &
b110 "
b110 %
#31
b0 !
b0 (
b10 #
b10 &
b100 "
b100 %
#32
b101 "
b101 %
