lab03dig/t03pos/t03pos.v
//Alejandro Rodríguez 19131
//Lab 3 t3 pos
module gates(); //creación de módulo
//variables
reg A,B,C,D; //in variables
wire w1,w2,w3,w4,w5,w6,w7,w8,w9; //or out variables
wire n1,n2,n3,n4; //not out variables
wire a1; //and out variable
not PnA(n1,A); //not gates para A, B, C y D
not PnB(n2,B);
not PnC(n3,C);
not PnD(n4,D);
or Pw1(w1,A,n2,C,D);//A+B'+C+D
or Pw2(w2,A,n2,C,n4);//A+B'+C+D'
or Pw3(w3,A,n2,n3,D);//A+B'+C'+D
or Pw4(w4,A,n2,n3,n4);//A+B'+C'+D'
or Pw5(w5,n1,B,C,n4);//A'+B+C+D'
or Pw6(w6,n1,B,n3,n4);//A'+B+C'+D'
or Pw7(w7,n1,n2,C,D);//A'+B'+C+D
or Pw8(w8,n1,n2,C,n4);//A'+B'+C+D'
or Pw9(w9,n1,n2,n3,n4);//A'+B'+C'+D'
and Pa1(a1,w1,w2,w3,w4,w5,w6,w7,w8,w9);//Y3
//comienzo
initial begin
    $display("A B C D | Y");
    $display("-----------");
    $monitor("%b %b %b %b | %b", A, B, C, D, a1);
    //condición inicial
    A = 0; B = 0; C = 0; D = 0;
    //simulación combinaciones
    #1 D = 1;
    #1 C = 1; D = 0;
    #1 D = 1;
    #1 B = 1; C = 0; D = 0;
    #1 D = 1;
    #1 C = 1; D = 0;
    #1 D = 1;
    #1 A = 1; B = 0; C = 0; D = 0;
    #1 D = 1;
    #1 C = 1; D = 0;
    #1 D = 1;
    #1 B = 1; C = 0; D = 0;
    #1 D = 1;
    #1 C = 1; D = 0;
    #1 D = 1;
    #1 $finish; //final de la simulación
end
initial
    begin
        $dumpfile("t03pos_tb.vcd"); //se crea archivo vcd
        $dumpvars(0,gates);
    end
endmodule //fin del módulo

lab03dig/t03pos/t03pos_tb.vcd
$date
	Fri Jul 31 22:53:35 2020
$end
$version
	Icarus Verilog
$end
$timescale
	1ps
$end
$scope module gates $end
$var wire 1 ! a1 $end
$var wire 1 " n1 $end
$var wire 1 # n2 $end
$var wire 1 $ n3 $end
$var wire 1 % n4 $end
$var wire 1 & w1 $end
$var wire 1 ' w2 $end
$var wire 1 ( w3 $end
$var wire 1 ) w4 $end
$var wire 1 * w5 $end
$var wire 1 + w6 $end
$var wire 1 , w7 $end
$var wire 1 - w8 $end
$var wire 1 . w9 $end
$var reg 1 / A $end
$var reg 1 0 B $end
$var reg 1 1 C $end
$var reg 1 2 D $end
$upscope $end
$enddefinitions $end
#0
$dumpvars
02
01
00
0/
1.
1-
1,
1+
1*
1)
1(
1'
1&
1%
1$
1#
1"
1!
$end
#1
0%
12
#2
1%
0$
02
11
#3
0%
12
#4
0!
1%
1'
0&
1$
0#
02
01
10
#5
0'
1&
0%
12
#6
0(
1%
1'
0$
02
11
#7
0)
1(
0%
12
#8
1!
1%
1$
1+
1*
1#
1)
0"
02
01
00
1/
#9
0!
0*
0%
12
#10
1!
1%
1*
0$
02
11
#11
0!
0+
0%
12
#12
1%
1-
0,
1$
1+
0#
02
01
10
#13
0-
1,
0%
12
#14
1!
1%
1-
0$
02
11
#15
0!
0.
0%
12
