lab10dig/E2/E2.v
//José Alejandro Rodríguez Porras 19131
//Electrónica Digital 1
//Laboratorio 10
//Ejercicio 2 ALU
//Flip Flop de 4 bits
//Flip Flop tipo D de 4 bits con Enable (acumulador)
module accu(input clk, rst, enable, input [3:0]d, output reg [3:0]q);
    always @ (posedge clk or posedge rst) begin
        if (rst) begin
            q <= 4'b0000;
        end
        else if (enable) begin
            q <= d;
        end
    end
endmodule

//Buffer Triestado de 4 bits 
module tribuf4(input enable, input [3:0]in, output wire [3:0]out);
    assign out = (enable) ? in:4'bz;

endmodule  
//ALU de 4 bits
module ALU(input [3:0]A, input [3:0]B, input [2:0]opcode, output reg [3:0]resultado, output reg Carry, output reg Zero); 

        reg [4:0]q; //Variable interna

        always @ (A or B or opcode) begin
            q = 5'b00000;
            // Depende de los casos del opcode se ejecuta una operación específica
            case(opcode)
                3'b000: begin
                            // Dejar pasar A
                            q = A;
                            Carry = 1'b0;
                        end

                3'b001: begin
                            // Comp
                            q = A - B; 
                            Carry = (q[4] == 5'b00000) ? 1:0;
 
                        end
                
                3'b010: begin
                            // Dejar pasar B
                            q = B;
                            Carry = 1'b0;
                        end

                3'b011: begin
                            // Suma
                            q = A + B;
                            Carry = (q[4] == 5'b00000) ? 1:0;
                        end

                3'b100: begin
                            // NAND
                            q = ~(A & B);
                            Carry = 1'b0;
                        end
            endcase
            Zero = (q == 5'b00000) ? 1:0;
            resultado = q[3:0];
        end
endmodule
//Módulo completo con los demás submodulos, es decir, el buffer triestado de 4 bits, el accu y la ALU
module alu_driver_accu(input [3:0]in, input clk, rst, en_accu, en1, en2, input [2:0]opcode, output wire Carry, Zero, output wire [3:0]out);
        wire [3:0]A;
        wire [3:0]B;
        wire [3:0]alu_out;
        //Entrada
        tribuf4 BT1(en1, in, B);
        //Acumulador
        accu DFF4(clk, rst, en_accu, alu_out, A);
        //ALU
        ALU alu(A, B, opcode, alu_out, Carry, Zero);
        //Salida
        tribuf4 BT2(en2, alu_out, out);
endmodule

lab10dig/E2/E2_tb.v
//José Alejandro Rodríguez Porras 19131
//Electrónica Digital 1
//Laboratorio 10
//Ejercicio 2 Testbench ALU
module testbench();
    //Declaración de variables
    reg en_accu, en1, en2, clk, rst;
    reg [3:0]in;
    reg [2:0]opcode;
    wire Carry, Zero;
    wire [3:0]out;
    //Asignación de módulos
    alu_driver_accu ADA(in, clk, rst, en_accu, en1, en2, opcode, Carry, Zero, out);
    //Prueba de funcionamiento de la ALU con acumulador y buses
    initial begin 
        $display("rst en_accu en1 en2 opcode in  | Carry Zero Out");
        $display("-------------------------------|---------------------------");
        $monitor("%b   %b       %b   %b   %b    %b| %b     %b    %b ", rst, en_accu, en1, en2, opcode, in, Carry, Zero, out);
        rst = 0; en_accu = 0; en1 = 0; en2 = 0; opcode = 3'b000; in = 4'b0000; clk = 0;
        //Prueba del reset
        #1  rst = 1; en_accu = 0; en1 = 0; en2 = 0; opcode = 3'b000; in = 4'b0000;
        //Prueba de que cuando todos los enables estan apagados la salida se pone en alta impedancia
        #1  rst = 0; en_accu = 0; en1 = 0; en2 = 0; opcode = 3'b000; in = 4'b0111;
        //Prueba de dejar pasar A y poniendo un input cualquiera
        #10 rst = 0; en_accu = 1; en1 = 1; en2 = 1; opcode = 3'b000; in = 4'b0111;
        //Prueba de dejar pasar B y poniendo un input cualquiera
        #10 rst = 0; en_accu = 1; en1 = 1; en2 = 1; opcode = 3'b010; in = 4'b0001;
        //Prueba de comparación entre A y B
        #10 rst = 0; en_accu = 1; en1 = 1; en2 = 1; opcode = 3'b001; in = 4'b1001;
        //Prueba de la suma entre A y B
        #10 rst = 0; en_accu = 1; en1 = 1; en2 = 1; opcode = 3'b011; in = 4'b1011;
        //Prueba de el NAND entre A y B
        #10 rst = 0; en_accu = 1; en1 = 1; en2 = 1; opcode = 3'b100; in = 4'b1010;
        //Prueba de apagar todos los enables
        #10 rst = 0; en_accu = 0; en1 = 0; en2 = 0; opcode = 3'b100; in = 4'b1100;
        //Prueba del reset asíncrono
        #10 rst = 1; en_accu = 1; en1 = 1; en2 = 1; opcode = 3'b000; in = 4'b1010;
        #1  rst = 0; en_accu = 1; en1 = 1; en2 = 1; opcode = 3'b000; in = 4'b0000;
        #200 $finish;
    end
    //Clock
    always
        #5 clk = ~clk;
    //Creación del diagrama de timing
    initial begin
        $dumpfile("E2_tb.vcd");
        $dumpvars(0,testbench);
    end
endmodule

lab10dig/E2/E2_tb.vcd
$date
	Sat Nov 07 23:17:59 2020
$end
$version
	Icarus Verilog
$end
$timescale
	1ps
$end
$scope module testbench $end
$var wire 4 ! out [3:0] $end
$var wire 1 " Zero $end
$var wire 1 # Carry $end
$var reg 1 $ clk $end
$var reg 1 % en1 $end
$var reg 1 & en2 $end
$var reg 1 ' en_accu $end
$var reg 4 ( in [3:0] $end
$var reg 3 ) opcode [2:0] $end
$var reg 1 * rst $end
$scope module ADA $end
$var wire 1 $ clk $end
$var wire 1 % en1 $end
$var wire 1 & en2 $end
$var wire 1 ' en_accu $end
$var wire 4 + in [3:0] $end
$var wire 3 , opcode [2:0] $end
$var wire 1 * rst $end
$var wire 4 - out [3:0] $end
$var wire 4 . alu_out [3:0] $end
$var wire 1 " Zero $end
$var wire 1 # Carry $end
$var wire 4 / B [3:0] $end
$var wire 4 0 A [3:0] $end
$scope module BT1 $end
$var wire 1 % enable $end
$var wire 4 1 in [3:0] $end
$var wire 4 2 out [3:0] $end
$upscope $end
$scope module BT2 $end
$var wire 1 & enable $end
$var wire 4 3 out [3:0] $end
$var wire 4 4 in [3:0] $end
$upscope $end
$scope module DFF4 $end
$var wire 1 $ clk $end
$var wire 1 ' enable $end
$var wire 1 * rst $end
$var wire 4 5 d [3:0] $end
$var reg 4 6 q [3:0] $end
$upscope $end
$scope module alu $end
$var wire 4 7 A [3:0] $end
$var wire 4 8 B [3:0] $end
$var wire 3 9 opcode [2:0] $end
$var reg 1 # Carry $end
$var reg 1 " Zero $end
$var reg 5 : q [4:0] $end
$var reg 4 ; resultado [3:0] $end
$upscope $end
$upscope $end
$upscope $end
$enddefinitions $end
#0
$dumpvars
bx ;
b0xxxx :
b0 9
bz 8
bx 7
bx 6
bx 5
bx 4
bz 3
bz 2
b0 1
bx 0
bz /
bx .
bz -
b0 ,
b0 +
0*
b0 )
b0 (
0'
0&
0%
0$
0#
x"
bz !
$end
#1
b0 .
b0 4
b0 5
b0 ;
1"
b0 :
b0 0
b0 6
b0 7
1*
#2
b111 (
b111 +
b111 1
0*
#5
1$
#10
0$
#12
b0 !
b0 -
b0 3
b111 /
b111 2
b111 8
1&
1%
1'
#15
1$
#20
0$
#22
b1 !
b1 -
b1 3
b1 /
b1 2
b1 8
b1 .
b1 4
b1 5
b1 ;
0"
b1 :
b1 (
b1 +
b1 1
b10 )
b10 ,
b10 9
#25
b1 :
b1 0
b1 6
b1 7
1$
#30
0$
#32
b1000 !
b1000 -
b1000 3
b1001 /
b1001 2
b1001 8
b1000 .
b1000 4
b1000 5
b1000 ;
0"
0#
b11000 :
b1001 (
b1001 +
b1001 1
b1 )
b1 ,
b1 9
#35
b1111 !
b1111 -
b1111 3
b1111 .
b1111 4
b1111 5
b1111 ;
b11111 :
b1000 0
b1000 6
b1000 7
1$
#40
0$
#42
b11 !
b11 -
b11 3
b1011 /
b1011 2
b1011 8
b11 .
b11 4
b11 5
b11 ;
b10011 :
b1011 (
b1011 +
b1011 1
b11 )
b11 ,
b11 9
#45
b1110 !
b1110 -
b1110 3
b1110 .
b1110 4
b1110 5
b1110 ;
1#
b1110 :
b11 0
b11 6
b11 7
1$
#50
0$
#52
b1101 !
b1101 -
b1101 3
b1010 /
b1010 2
b1010 8
b1101 .
b1101 4
b1101 5
b1101 ;
0#
b11101 :
b1010 (
b1010 +
b1010 1
b100 )
b100 ,
b100 9
#55
b111 !
b111 -
b111 3
b111 .
b111 4
b111 5
b111 ;
b10111 :
b1101 0
b1101 6
b1101 7
1$
#60
0$
#62
bx1x .
bx1x 4
bx1x 5
bx1x ;
b1xx1x :
bz !
bz -
bz 3
bz /
bz 2
bz 8
b1100 (
b1100 +
b1100 1
0&
0%
0'
#65
1$
#70
0$
#72
1"
b0 0
b0 6
b0 7
b0 .
b0 4
b0 5
b0 ;
b0 :
b0 !
b0 -
b0 3
b1010 /
b1010 2
b1010 8
b1010 (
b1010 +
b1010 1
b0 )
b0 ,
b0 9
1&
1%
1'
1*
#73
b0 /
b0 2
b0 8
b0 (
b0 +
b0 1
0*
