lab06dig/E5/E5.v
//José Alejandro Rodríguez Porras 19131
//Electrónica Digital
//Laboratorio 6
//Ejercicio 5: Flip Flop Tipo D de 4 Bits con reset asíncrono y un set síncrono
module dff4(input clk, rst, input [3:0] d, output reg [3:0] q); 
    //lista sensible de variables con clock y reset y las instrucciones que se ejecutan 
    always @ (posedge clk or posedge rst) begin
        if (rst)
            q <= 4'b0;
        else
            q <= d;
    end
endmodule

lab06dig/E5/E5_tb.v
//Alejandro Rodríguez 19131
//Lab 6
//testbench
module testbench();
    reg clk, rst;
    reg [3:0] d;
    wire [3:0] q;
    dff4 FF1(clk, rst, d, q);
    
 // Prueba del funcionamiento del flip flop tipo D de 4 bits   
    initial begin
        clk = 0; rst = 0; d = 4'b0000;
        #1 rst = 1;
        #1 rst = 0;
        #11 d = 4'b0001;
        #11 d = 4'b0101;
        #15 d = 4'b1111;
        //Prueba del reset asíncrono en un flanco negativo
        #1 rst = 1;
        #1 rst = 0;
        #9 d = 4'b1101;
        #9 d = 4'b1001;
        #8 d = 4'b0111;
        #100 $finish;
    end 
    //generación del reloj con período de 10 unidades de tiempo
    always
        #5 clk = ~clk;
    initial begin
        $dumpfile("E5_tb.vcd");
        $dumpvars(0,testbench);
    end
endmodule

lab06dig/E5/E5_tb.vcd
$date
	Sat Sep 05 17:41:18 2020
$end
$version
	Icarus Verilog
$end
$timescale
	1ps
$end
$scope module testbench $end
$var wire 4 ! q [3:0] $end
$var reg 1 " clk $end
$var reg 4 # d [3:0] $end
$var reg 1 $ rst $end
$scope module FF1 $end
$var wire 1 " clk $end
$var wire 4 % d [3:0] $end
$var wire 1 $ rst $end
$var reg 4 & q [3:0] $end
$upscope $end
$upscope $end
$enddefinitions $end
#0
$dumpvars
bx &
b0 %
0$
b0 #
0"
bx !
$end
#1
b0 !
b0 &
1$
#2
0$
#5
1"
#10
0"
#13
b1 #
b1 %
#15
b1 !
b1 &
1"
#20
0"
#24
b101 #
b101 %
#25
b101 !
b101 &
1"
#30
0"
#35
1"
#39
b1111 #
b1111 %
#40
b0 !
b0 &
1$
0"
#41
0$
#45
b1111 !
b1111 &
1"
#50
0"
b1101 #
b1101 %
#55
b1101 !
b1101 &
1"
#59
b1001 #
b1001 %
#60
0"
#65
b1001 !
b1001 &
1"
#67
b111 #
b111 %
#70
0"
#75
b111 !
b111 &
1"
