lab04dig/ejercicio05/ejercicio05.v
//José Alejandro Rodríguez Porras 19131
//Electrónica Digital
//Lab 4 Ejercicio 5
//Variables:
//A = Sistema de Alarma : 1 = armado
//V = sensor de ventana/puerta : 1 = OK
//M = sensor de movimiento : 0 = no movimiento
//L = Alarma y luces encendidas : 1 = se enciende
//Módulos con Gate Level Modelling
//SOP = AV'M'+AV'M+AVM
module gsop05(input wire A, V, M, output wire L);

    wire nv, nm, w1, w2, w3;
    
    not (nv, V);
    not (nm, M);
    and (w1, A, nv, nm);
    and (w2, A, nv, M);
    and (w3, A, V, M);
    or (L, w1, w2, w3);

endmodule

//POS = (A+V+M)*(A+V+M')*(A+V'+M)*(A+V'+M')*(A'+V'+M)
module gpos05(input wire A, V, M, output wire L);

    wire na, nv, nm, w1, w2, w3, w4, w5;
    
    not (na, A);
    not (nv, V);
    not (nm, M);
    or (w1, A, V, M);
    or (w2, A, V, nm);
    or (w3, A, nv, M);
    or (w4, A, nv, nm);
    or (w5, na, nv, M);
    and (L, w1, w2, w3, w4, w5);

endmodule

//Ecuación minimizada con mapa de Karnaugh: Y = AV'+AM
module g05(input wire A, V, M, output wire L);

    wire nv, w1, w2;

    not (nv, V);
    and (w1, A, nv);
    and (w2, A, M);
    or (L, w1, w2);

endmodule

//Módulos con Behavioral Modelling
//SOP = AV'M'+AV'M+AVM
module opsop05(input wire A, V, M, output wire L);

    assign L = (A & ~V & ~M) | (A & ~V & M) | (A & V & M);

endmodule

//POS = (A+V+M)*(A+V+M')*(A+V'+M)*(A+V'+M')*(A'+V'+M)
 module oppos05(input wire A, V, M, output wire L);

    assign L = (A | V | M) & (A | V | ~M) & (A | ~V | M) & (A | ~V | ~M) & (~A | ~V | M);

endmodule

//Ecuación minimizada con mapa de Karnaugh: Y = AV'+AM
module op05(input wire A, V, M, output L);

    assign L = (A & ~V) | (A & M);

endmodule

lab04dig/ejercicio05/ejercicio05_tb.v
// José Alejandro Rodríguez Porras 19131
//testbench
module testbench();

    //definir variables de inputs para cada ecuación
    reg gsopA, gsopV, gsopM, gposA, gposV, gposM, g5A, g5V, g5M,
    opsopA, opsopV, opsopM, opposA, opposV, opposM, op5A, op5V, op5M;
    wire gsopL, gposL, g5L, opsopL, opposL, op5L;
    //asignación de las variables a cada uno de los módulos
    //módulos con gate level modelling 
    gsop05 GS5(gsopA, gsopV, gsopM, gsopL);
    gpos05 GP5(gposA, gposV, gposM, gposL);
    g05 G5(g5A, g5V, g5M, g5L);

    //módulos con operadores lógicos
    opsop05 OPS5(opsopA, opsopV, opsopM, opsopL);
    oppos05 OPP5(opposA, opposV, opposM, opposL);
    op05 OP5(op5A, op5V, op5M, op5L);

    //Simulaciones de los módulos con gate level modelling
    //Simulación sop 
    initial begin
        $display("A B C | Y");
        $display("------|--");
        $monitor("%b %b %b | %b", gsopA, gsopV, gsopM, gsopL);
        gsopA = 0; gsopV = 0; gsopM = 0;
        #1 gsopA = 0; gsopV = 0; gsopM = 1;
        #1 gsopA = 0; gsopV = 1; gsopM = 0;
        #1 gsopA = 0; gsopV = 1; gsopM = 1;
        #1 gsopA = 1; gsopV = 0; gsopM = 0;
        #1 gsopA = 1; gsopV = 0; gsopM = 1;
        #1 gsopA = 1; gsopV = 1; gsopM = 0;
        #1 gsopA = 1; gsopV = 1; gsopM = 1;
    end

    //Simulación pos
    initial begin
        #8
        $display("\n");
        $display("A B C | Y");
        $display("------|--");
        $monitor("%b %b %b | %b", gposA, gposV, gposM, gposL);
        gposA = 0; gposV = 0; gposM = 0;
        #1 gposA = 0; gposV = 0; gposM = 1;
        #1 gposA = 0; gposV = 1; gposM = 0;
        #1 gposA = 0; gposV = 1; gposM = 1;
        #1 gposA = 1; gposV = 0; gposM = 0;
        #1 gposA = 1; gposV = 0; gposM = 1;
        #1 gposA = 1; gposV = 1; gposM = 0;
        #1 gposA = 1; gposV = 1; gposM = 1;
    end

    //Simulación ecuación minimizada
    initial begin
        #16
        $display("\n");
        $display("A B C | Y");
        $display("------|--");
        $monitor("%b %b %b | %b", g5A, g5V, g5M, g5L);
        g5A = 0; g5V = 0; g5M = 0;
        #1 g5A = 0; g5V = 0; g5M = 1;
        #1 g5A = 0; g5V = 1; g5M = 0;
        #1 g5A = 0; g5V = 1; g5M = 1;
        #1 g5A = 1; g5V = 0; g5M = 0;
        #1 g5A = 1; g5V = 0; g5M = 1;
        #1 g5A = 1; g5V = 1; g5M = 0;
        #1 g5A = 1; g5V = 1; g5M = 1;
    end

    //Simulación de los módulos con behavioral modelling
    //Simulación sop
    initial begin
        #24
        $display("\n");
        $display("A B C | Y");
        $display("------|--");
        $monitor("%b %b %b | %b", opsopA, opsopV, opsopM, opsopL);
        opsopA = 0; opsopV = 0; opsopM = 0;
        #1 opsopA = 0; opsopV = 0; opsopM = 1;
        #1 opsopA = 0; opsopV = 1; opsopM = 0;
        #1 opsopA = 0; opsopV = 1; opsopM = 1;
        #1 opsopA = 1; opsopV = 0; opsopM = 0;
        #1 opsopA = 1; opsopV = 0; opsopM = 1;
        #1 opsopA = 1; opsopV = 1; opsopM = 0;
        #1 opsopA = 1; opsopV = 1; opsopM = 1;
    end

    //Simulación pos
    initial begin
        #32
        $display("\n");
        $display("A B C | Y");
        $display("------|--");
        $monitor("%b %b %b | %b", opposA, opposV, opposM, opposL);
        opposA = 0; opposV = 0; opposM = 0;
        #1 opposA = 0; opposV = 0; opposM = 1;
        #1 opposA = 0; opposV = 1; opposM = 0;
        #1 opposA = 0; opposV = 1; opposM = 1;
        #1 opposA = 1; opposV = 0; opposM = 0;
        #1 opposA = 1; opposV = 0; opposM = 1;
        #1 opposA = 1; opposV = 1; opposM = 0;
        #1 opposA = 1; opposV = 1; opposM = 1;
    end

    //Simulación ecuación minimizada
    initial begin
        #40
        $display("\n");
        $display("A B C | Y");
        $display("------|--");
        $monitor("%b %b %b | %b", op5A, op5V, op5M, op5L);
        op5A = 0; op5V = 0; op5M = 0;
        #1 op5A = 0; op5V = 0; op5M = 1;
        #1 op5A = 0; op5V = 1; op5M = 0;
        #1 op5A = 0; op5V = 1; op5M = 1;
        #1 op5A = 1; op5V = 0; op5M = 0;
        #1 op5A = 1; op5V = 0; op5M = 1;
        #1 op5A = 1; op5V = 1; op5M = 0;
        #1 op5A = 1; op5V = 1; op5M = 1;
    end

    initial
    #49 $finish;

//generación del archivo vcd  
  initial begin
    $dumpfile("ejercicio05_tb.vcd");
    $dumpvars(0, testbench);
  end
  
endmodule

lab04dig/ejercicio05/ejercicio05_tb.vcd
$date
	Sun Aug 09 14:13:45 2020
$end
$version
	Icarus Verilog
$end
$timescale
	1ps
$end
$scope module testbench $end
$var wire 1 ! opsopL $end
$var wire 1 " opposL $end
$var wire 1 # op5L $end
$var wire 1 $ gsopL $end
$var wire 1 % gposL $end
$var wire 1 & g5L $end
$var reg 1 ' g5A $end
$var reg 1 ( g5M $end
$var reg 1 ) g5V $end
$var reg 1 * gposA $end
$var reg 1 + gposM $end
$var reg 1 , gposV $end
$var reg 1 - gsopA $end
$var reg 1 . gsopM $end
$var reg 1 / gsopV $end
$var reg 1 0 op5A $end
$var reg 1 1 op5M $end
$var reg 1 2 op5V $end
$var reg 1 3 opposA $end
$var reg 1 4 opposM $end
$var reg 1 5 opposV $end
$var reg 1 6 opsopA $end
$var reg 1 7 opsopM $end
$var reg 1 8 opsopV $end
$scope module G5 $end
$var wire 1 ' A $end
$var wire 1 & L $end
$var wire 1 ( M $end
$var wire 1 ) V $end
$var wire 1 9 nv $end
$var wire 1 : w1 $end
$var wire 1 ; w2 $end
$upscope $end
$scope module GP5 $end
$var wire 1 * A $end
$var wire 1 % L $end
$var wire 1 + M $end
$var wire 1 , V $end
$var wire 1 < na $end
$var wire 1 = nm $end
$var wire 1 > nv $end
$var wire 1 ? w1 $end
$var wire 1 @ w2 $end
$var wire 1 A w3 $end
$var wire 1 B w4 $end
$var wire 1 C w5 $end
$upscope $end
$scope module GS5 $end
$var wire 1 - A $end
$var wire 1 $ L $end
$var wire 1 . M $end
$var wire 1 / V $end
$var wire 1 D nm $end
$var wire 1 E nv $end
$var wire 1 F w1 $end
$var wire 1 G w2 $end
$var wire 1 H w3 $end
$upscope $end
$scope module OP5 $end
$var wire 1 0 A $end
$var wire 1 # L $end
$var wire 1 1 M $end
$var wire 1 2 V $end
$upscope $end
$scope module OPP5 $end
$var wire 1 3 A $end
$var wire 1 " L $end
$var wire 1 4 M $end
$var wire 1 5 V $end
$upscope $end
$scope module OPS5 $end
$var wire 1 6 A $end
$var wire 1 ! L $end
$var wire 1 7 M $end
$var wire 1 8 V $end
$upscope $end
$upscope $end
$enddefinitions $end
#0
$dumpvars
0H
0G
0F
1E
1D
xC
xB
xA
x@
x?
x>
x=
x<
x;
x:
x9
x8
x7
x6
x5
x4
x3
x2
x1
x0
0/
0.
0-
x,
x+
x*
x)
x(
x'
x&
x%
0$
x#
x"
x!
$end
#1
0D
1.
#2
1D
0E
0.
1/
#3
0D
1.
#4
1$
1F
1D
1E
0.
0/
1-
#5
0F
0D
1G
1.
#6
0$
1D
0G
0E
0.
1/
#7
1$
0D
1H
1.
#8
0%
1@
1A
1B
1=
1C
1>
1<
0?
0+
0,
0*
#9
0%
0@
0=
1?
1+
#10
1=
0A
0>
1@
0+
1,
#11
0%
0B
0=
1A
1+
#12
1%
1=
1>
0<
1B
0+
0,
1*
#13
0=
1+
#14
0%
1=
0C
0>
0+
1,
#15
1%
0=
1C
1+
#16
0&
19
0:
0;
0(
0)
0'
#17
1(
#18
09
0(
1)
#19
1(
#20
1&
1:
19
0(
0)
1'
#21
1;
1(
#22
0&
0:
0;
09
0(
1)
#23
1&
1;
1(
#24
0!
07
08
06
#25
17
#26
07
18
#27
17
#28
1!
07
08
16
#29
17
#30
0!
07
18
#31
1!
17
#32
0"
04
05
03
#33
14
#34
04
15
#35
14
#36
1"
04
05
13
#37
14
#38
0"
04
15
#39
1"
14
#40
0#
01
02
00
#41
11
#42
01
12
#43
11
#44
1#
01
02
10
#45
11
#46
0#
01
12
#47
1#
11
