uP/uP/uP.v
//José Alejandro Rodríguez Porras 19131
//Electrónica Digital 1
//Proyecto 2 uP
//Módulo del flip flop D de 1 bit
module FFD1(input clk, rst, enable, d, output reg q);
    always @ (posedge clk or posedge rst) begin
        if (rst)
            q <= 0;
        else if (enable)
            q <= d;
        end 
endmodule
//Módulo del flip flop D de 2 bits
module FFD2(input clk, rst, enable, input [1:0]d, output reg [1:0]q);
    always @ (posedge clk or posedge rst) begin
        if (rst)
            q <= 2'b0;
        else if (enable)
            q <= d;
        end 
endmodule
//Módulo del flip flop D de 4 bits
module FFD4(input clk, rst, enable, input [3:0]d, output reg [3:0]q);
    always @ (posedge clk or posedge rst) begin
        if (rst)
            q <= 4'b0;
        else if (enable)
            q <= d;
        end 
endmodule

//Módulo del flip flop de 8 bits con dos salidas separadas de 4 bits
module FFD8(input wire clk, rst, enable, input wire [7:0]d, output wire [3:0]q1, output wire [3:0]q0);
    FFD4 f1(clk, rst, enable, d[7:4], q1);
    FFD4 f2(clk, rst, enable, d[3:0], q0);
endmodule

//Flip Flop tipo T con Enable para el Phase
module FFT(input wire clk, rst, enable, output wire q);
    FFD1 ffd1(clk, rst, enable, ~q, q);
endmodule

//Buffer Triestado de 4 bits
module tribuf4(input wire enable, input wire [3:0]in, output wire [3:0]out);
    assign out = (enable) ? in:4'bz;
endmodule

//Módulo del counter
module upcounter(input clk, rst, enabled, load, input [11:0]loadvalue, output reg [11:0]counter);
    // reset asíncrono
    always @ (posedge clk or posedge rst) begin
        if (rst)
            counter = 12'b0;
            // El reset pone todos los bits en 0.
        else if (load)
            counter = loadvalue;
            // El Load asigna un valor específico(Loadvalue) al contador mientras Load sea igual a 1
        else if (enabled)
            counter = counter + 1;
            //Mientras el enabled esté activado el counter sube 1 cada flanco positivo de reloj
    end

endmodule

//Memoria ROM de 4k x 8
//input es la dirección de memoria en la que se guarda el valor
//output es el dato que se almacena en la dirección
module rom(input wire [11:0]direccion, output wire [7:0]data);
    reg [7:0] memoria[0:4095];
    initial begin 
    // readmemb lee el archivo lista y almacena sus datos en una variable
        $readmemh("memory.list", memoria);
    end
    //asignación del dato en la dirección de la memoria
    assign data = memoria[direccion];
endmodule

//ALU de 4 bits del proyecto con inputs A, B como operandos, y op para elegir la operación que se desea realizar
//C y Zero son las banderas que se activan cuando hay overflow o la salida es 0 respectivamente
//S representa la salida de la ALU
module alu(input [3:0] A, B, input [2:0] op, output C, Zero, output [3:0]out);
    //Variable interna de salida de la operación
    //El quinto bit es para indicar overflow
    reg [4:0] pseudoout;
    //case para realizar la operación indicada dependiendo de la combinación de op y se actualiza cada vez que cambia A, B o op.
    always @ (A, B, op)
        case (op)
            3'b000: pseudoout = A; //Dejar pasar A
            3'b001: pseudoout = A - B; //Comparar A y B (Resta A-B)
            3'b010: pseudoout = B; //Dejar pasar B
            3'b011: pseudoout = A + B; // Sumar A y B
            3'b100: pseudoout = {1'b0, ~(A & B)}; //NAND entre a y B
            default: pseudoout = 5'b10101; //Default
        endcase
    //Asignación de las salidas con los bits de la variable interna de operación
    //Asigna del bit 4 al 0 de la variable interna a la salida de la ALU
    assign out = pseudoout[3:0];
    //Asigna el bit 5 para la bandera de carry cuando hay overflow
    assign C = pseudoout[4];
    //Identifica cuando el bit 4 al 0 todos son 0s, es decir la bandera Zero solo se activa cuando la salida de la operación es 0000.
    assign Zero = ~(pseudoout[3] | pseudoout[2] | pseudoout[1] | pseudoout[0]);
    
endmodule

//Módulo del decode, con el que se controlan todas las señales del procesador
//los inputs son los bits de instruccion, carry, zero y phase concatenados
//los outputs son para incPC, loadPC, loadA, loadFlags, S2, S1, S0, csRAM, weRAM, oeALU, oeIN, oeOprnd, loadOut respectivamente
//con lo que se controlan muchos de los enables de cada submódulos
//Es como el cerebro del microprocesador debido a que con este se controlan todas las señales
module decode(input [6:0]direccion, output [12:0]controlS);
    //variable interna para la salida del decoder 
    reg [12:0] pseudocontrolS;
    //siempre que haya un cambio en la combinación de la dirección de inputs se actualiza la variable interna de salida usando un casez
    always @ (direccion)
        casex(direccion)
            // any
            7'bxxxx_xx0: pseudocontrolS <= 13'b1000000001000;
            // JC
            7'b0000_1x1: pseudocontrolS <= 13'b0100000001000;
            7'b0000_0x1: pseudocontrolS <= 13'b1000000001000;
            // JNC
            7'b0001_1x1: pseudocontrolS <= 13'b1000000001000;
            7'b0001_0x1: pseudocontrolS <= 13'b0100000001000;
            // CMPI
            7'b0010_xx1: pseudocontrolS <= 13'b0001001000010;
            // CMPM
            7'b0011_xx1: pseudocontrolS <= 13'b1001001100000;
            // LIT
            7'b0100_xx1: pseudocontrolS <= 13'b0011010000010;
            // IN
            7'b0101_xx1: pseudocontrolS <= 13'b0011010000100;
            // LD
            7'b0110_xx1: pseudocontrolS <= 13'b1011010100000;
            // ST
            7'b0111_xx1: pseudocontrolS <= 13'b1000000111000;
            // JZ
            7'b1000_x11: pseudocontrolS <= 13'b0100000001000;
            7'b1000_x01: pseudocontrolS <= 13'b1000000001000;
            // JNZ
            7'b1001_x11: pseudocontrolS <= 13'b1000000001000;
            7'b1001_x01: pseudocontrolS <= 13'b0100000001000;
            // ADDI
            7'b1010_xx1: pseudocontrolS <= 13'b0011011000010;
            // ADDM
            7'b1011_xx1: pseudocontrolS <= 13'b1011011100000;
            // JMP
            7'b1100_xx1: pseudocontrolS <= 13'b0100000001000;
            // OUT
            7'b1101_xx1: pseudocontrolS <= 13'b0000000001001;
            // NANDI
            7'b1110_xx1: pseudocontrolS <= 13'b0011100000010;
            // NANDM
            7'b1111_xx1: pseudocontrolS <= 13'b1011100100000;
            default: pseudocontrolS <= 13'b1111111111111;
        endcase
    //se asigna el valor de la variable interna de salida a la variable externa de salida controlS    
    assign controlS = pseudocontrolS;
endmodule

//Módulo de la RAM, con input de la dirección address_RAM, resultado de la concatenación de oprnd y program_byte 
//El data_bus es un inout ya que funciona como input cuando el write enable es 1 y el chip select es 1
//El data_bus es un output cuando el writeenable es 0 y el chip select es 1.
//chip select es csRAM y write enable es weRAM
module ram(input [11:0]address_RAM, inout [3:0]data_bus, input csRAM, weRAM);
    //Variable interna de bus de salida
    reg [3:0]data_out;
    //Memoria ram
    reg [3:0] mem[0:4095];
    //asignación de la variable externa de bus de salida dependiendo de la condición
    //si solo chip select está activado se actualiza con el valor de la variable interna
    //si write enable está activado la salida se pone en alta impedancia
    assign data_bus = (csRAM && !weRAM) ? data_out : 4'bz;
    //Con el bloque always se incluye en la lista de sensibilidad la dirección, el bus de datos, el chip select y el write enable
    always @ (address_RAM or data_bus or csRAM or weRAM) begin
        //Si chip select y write enable están en 1, entonces se le asigna al valor del data_bus, como input al address_RAM
        //Función write 
        if (csRAM && weRAM) begin 
            mem[address_RAM] = data_bus;
        end
        //Si el chip select está en 1 y write enable en 0, entonces se le asigna el valor de la dirección a la variable de salida de bus interna 
        //Función read
        if (csRAM && !weRAM) begin 
            data_out = mem[address_RAM];
        end
    end
endmodule

//Módulo uP completo
module uP(input clock, reset, input [3:0]pushbuttons, output wire phase, c_flag, z_flag, output wire [3:0]instr, output wire [3:0]oprnd, output wire [3:0]accu,
output wire [3:0]data_bus, output wire [3:0]FF_out, output wire [7:0]program_byte, output wire [11:0]PC, output wire [11:0]address_RAM);
    
    //Cables internos 
    //outputs de la tabla
    // Program counter/ Accu/ Flags c y z/ op de ALU/      RAM    / ALU   /inputs/ oprnd/ outputs / flags 
    wire incPC, loadPC, loadA, loadFlags, S2, S1, S0, csRAM, weRAM, oeALU, oeIN, oeOprnd, loadOut, C, Zero;
    //Salida de la ALU
    wire [3:0]ALUout;
    //concatenación del operando y el program_byte para formar el address_RAM
    assign address_RAM = {oprnd, program_byte};
    //ingreso de las variables respectivas al program counter cuya salida es PC
    upcounter PROGRAMCOUNTER(clock, reset, incPC, loadPC, address_RAM, PC);
    //ingreso del input de PC y salida de program_byte a la rom
    rom ROM(PC, program_byte);
    //ingreso de las variables respectivas al fetch, donde el fetch se habilita cuando el phase es 0 únicamente, debido a que su enable es ~phase
    FFD8 FETCH(clock, reset, ~phase, program_byte, instr, oprnd);
    //ingreso de variables al modulo fetch, con 1'b1 ingresado en el enable para que que siempre esté activo,  funcionando como un clock con doble período
    //ya que un ciclo de phase dura dos ciclos de reloj
    FFT PHASE(clock, reset, 1'b1, phase);
    //Ingreso de variables respectivas al a ram
    ram RAM(address_RAM, data_bus, csRAM, weRAM);
    //Ingreso de inputs concatenados y outputs concatenados del decode
    decode DECODE({instr, c_flag, z_flag, phase}, {incPC, loadPC, loadA, loadFlags, S2, S1, S0, csRAM, weRAM, oeALU, oeIN, oeOprnd, loadOut});
    //buffer triestado para el bus del operando proveniente de la salida del fetch, y cuya salida es el data_bus
    tribuf4 BUSOPRND(oeOprnd, oprnd, data_bus);
    //ALU del proyecto con la combinación de op S2, S1 y S0 concatenada y cuya salida es el cable ALUout
    alu ALU(accu, data_bus,  {S2, S1, S0}, C, Zero, ALUout);
    //módulo de acumulador con respectivos enables
    FFD4 ACCU(clock, reset, loadA, ALUout, accu);
    //buffer triestado para la salida de la alu, donde ALUout es un input y data_bus es la salida
    tribuf4 BUSALU(oeALU, ALUout, data_bus);
    //flip flop de 2 bits para las banderas de Carry y Zero, concatenadas para el input, y que tienen como output c_flag y z_flag concatenadas
    FFD2 FLAGS(clock, reset, loadFlags, {C, Zero}, {c_flag, z_flag});
    //flip flop de 4 bits para el módulo de outputs, teniendo como entrada el data_bus y salida el FF_out. 
    FFD4 OUTPUTS(clock, reset, loadOut, data_bus, FF_out);
    //buffer triestado para el bus del módulo inputs, con entrada de 4 bits de pushbuttons y 4 bits salida de data_bus.
    tribuf4 BUSIN(oeIN, pushbuttons, data_bus);

endmodule

uP/uPtbpropio/uP_tb.v
//José Alejandro Rodríguez Porras 19131
//Electrónica Digital 1
//Proyecto 2 uP
module testbench();
    reg clock, reset;
    reg [3:0] pushbuttons;
    wire phase, c_flag, z_flag;
    wire [3:0] instr, oprnd, accu, data_bus, FF_out;
    wire [7:0] program_byte;
    wire [11:0] PC, address_RAM;

    uP uPmodulue(clock, reset, pushbuttons, phase, c_flag, z_flag, instr, oprnd, accu, data_bus, FF_out, program_byte, PC, address_RAM);
    initial
        #1000 $finish;
    
    always 
        #5 clock = ~clock;
    
    initial begin
        clock = 0; reset = 0; pushbuttons = 4'b0110;
        #2 reset = 1;
        #1 reset = 0;
    end
    initial begin
        $dumpfile("uP_tb.vcd");
        $dumpvars(0, testbench);
    end
    initial begin
        #16
        if (accu === 4'hF) begin
            $display("Módulo ACCU funciona correctamente");
        end
        else
            $display("Módulo ACCU NO funciona correctamente");
    end

    initial begin
        #116
        if (c_flag === 1'b1 && z_flag === 1'b0 && data_bus === 4'h9) begin
            $display("Módulo ALU y buffer triestado ALU funciona correctamente");
        end
        else
            $display("Módulo ALU y/o buffer triestado ALU NO funciona correctamente");
    end

    initial begin
        #247
        if (data_bus === 4'h6) begin
            $display("Módulo INPUTS funciona correctamente");
        end
        else
            $display("Módulo INPUTS NO funciona correctamente");
    end
    
    initial begin
        #287
        if (data_bus === 4'hF) begin
            $display("Módulo BUSOPRND funciona correctamente");
        end
        else
            $display("Módulo BUSOPRND NO funciona correctamente");
    end

    initial begin
        #296
        if ( {instr, c_flag, z_flag, phase} === 7'h20 && accu === 4'hF) begin
            $display("Módulo DECODE funciona correctamente");
        end
        else
            $display("Módulo DECODE NO funciona correctamente");
    end

    initial begin
        #297
        if ( instr === 4'h4 && oprnd === 4'hF && program_byte === 8'h71) begin
            $display("Módulo FETCH funciona correctamente");
        end
        else
            $display("Módulo FETCH NO funciona correctamente");
    end
    initial begin
        #92
        if ( c_flag === 1'b0 && z_flag === 1'b1) begin
            $display("Módulo FLAGS funciona correctamente");
        end
        else
            $display("Módulo FLAGS NO funciona correctamente");
    end
    initial begin
        #238
        if ( FF_out === 4'h4 && instr === 4'hD && c_flag === 1'b0 && z_flag === 1'b0 && phase === 1'b0) begin
            $display("Módulo OUTPUTS funciona correctamente");
        end
        else
            $display("Módulo OUTPUTS NO funciona correctamente");
    end
    initial begin
        #6
        if (phase === 1'b1) begin
            $display("Módulo PHASE funciona correctamente");
        end
        else
            $display("Módulo PHASE NO funciona correctamente");
    end
    initial begin
        #14
        if (phase === 1'b1) begin
            $display("Módulo PHASE funciona correctamente");
        end
        else
            $display("Módulo PHASE NO funciona correctamente");
    end
    initial begin
        #209
        if (PC === 12'h00B) begin
            $display("Módulo PROGRAMCOUNTER funciona correctamente");
        end
        else
            $display("Módulo PROGRAMCOUNTER NO funciona correctamente");
    end
    initial begin
        #209
        if (PC === 12'h00B) begin
            $display("Módulo PROGRAMCOUNTER funciona correctamente");
        end
        else
            $display("Módulo PROGRAMCOUNTER NO funciona correctamente");
    end
    initial begin
        #109
        if (address_RAM === 12'hA28 && data_bus == 4'hA) begin
            $display("Módulo RAM funciona correctamente");
        end
        else
            $display("Módulo RAM NO funciona correctamente");
    end
    initial begin
        #9
        if (program_byte === 8'hDF && PC == 12'h001) begin
            $display("Módulo ROM funciona correctamente");
        end
        else
            $display("Módulo ROM NO funciona correctamente");
    end
endmodule

uP/uPtbpropio/uP_tb.vcd
$date
	Sun Nov 22 21:43:38 2020
$end
$version
	Icarus Verilog
$end
$timescale
	1ps
$end
$scope module testbench $end
$var wire 4 ! data_bus [3:0] $end
$var wire 1 " z_flag $end
$var wire 8 # program_byte [7:0] $end
$var wire 1 $ phase $end
$var wire 4 % oprnd [3:0] $end
$var wire 4 & instr [3:0] $end
$var wire 1 ' c_flag $end
$var wire 12 ( address_RAM [11:0] $end
$var wire 4 ) accu [3:0] $end
$var wire 12 * PC [11:0] $end
$var wire 4 + FF_out [3:0] $end
$var reg 1 , clock $end
$var reg 4 - pushbuttons [3:0] $end
$var reg 1 . reset $end
$scope module uPmodulue $end
$var wire 1 , clock $end
$var wire 4 / data_bus [3:0] $end
$var wire 4 0 pushbuttons [3:0] $end
$var wire 1 . reset $end
$var wire 1 " z_flag $end
$var wire 1 1 weRAM $end
$var wire 8 2 program_byte [7:0] $end
$var wire 1 $ phase $end
$var wire 4 3 oprnd [3:0] $end
$var wire 1 4 oeOprnd $end
$var wire 1 5 oeIN $end
$var wire 1 6 oeALU $end
$var wire 1 7 loadPC $end
$var wire 1 8 loadOut $end
$var wire 1 9 loadFlags $end
$var wire 1 : loadA $end
$var wire 4 ; instr [3:0] $end
$var wire 1 < incPC $end
$var wire 1 = csRAM $end
$var wire 1 ' c_flag $end
$var wire 12 > address_RAM [11:0] $end
$var wire 4 ? accu [3:0] $end
$var wire 1 @ Zero $end
$var wire 1 A S2 $end
$var wire 1 B S1 $end
$var wire 1 C S0 $end
$var wire 12 D PC [11:0] $end
$var wire 4 E FF_out [3:0] $end
$var wire 1 F C $end
$var wire 4 G ALUout [3:0] $end
$scope module ACCU $end
$var wire 1 , clk $end
$var wire 1 : enable $end
$var wire 1 . rst $end
$var wire 4 H d [3:0] $end
$var reg 4 I q [3:0] $end
$upscope $end
$scope module ALU $end
$var wire 4 J A [3:0] $end
$var wire 4 K B [3:0] $end
$var wire 1 @ Zero $end
$var wire 3 L op [2:0] $end
$var wire 4 M out [3:0] $end
$var wire 1 F C $end
$var reg 5 N pseudoout [4:0] $end
$upscope $end
$scope module BUSALU $end
$var wire 1 6 enable $end
$var wire 4 O in [3:0] $end
$var wire 4 P out [3:0] $end
$upscope $end
$scope module BUSIN $end
$var wire 1 5 enable $end
$var wire 4 Q in [3:0] $end
$var wire 4 R out [3:0] $end
$upscope $end
$scope module BUSOPRND $end
$var wire 1 4 enable $end
$var wire 4 S out [3:0] $end
$var wire 4 T in [3:0] $end
$upscope $end
$scope module DECODE $end
$var wire 7 U direccion [6:0] $end
$var wire 13 V controlS [12:0] $end
$var reg 13 W pseudocontrolS [12:0] $end
$upscope $end
$scope module FETCH $end
$var wire 1 , clk $end
$var wire 1 X enable $end
$var wire 1 . rst $end
$var wire 4 Y q1 [3:0] $end
$var wire 4 Z q0 [3:0] $end
$var wire 8 [ d [7:0] $end
$scope module f1 $end
$var wire 1 , clk $end
$var wire 4 \ d [3:0] $end
$var wire 1 X enable $end
$var wire 1 . rst $end
$var reg 4 ] q [3:0] $end
$upscope $end
$scope module f2 $end
$var wire 1 , clk $end
$var wire 4 ^ d [3:0] $end
$var wire 1 X enable $end
$var wire 1 . rst $end
$var reg 4 _ q [3:0] $end
$upscope $end
$upscope $end
$scope module FLAGS $end
$var wire 1 , clk $end
$var wire 2 ` d [1:0] $end
$var wire 1 9 enable $end
$var wire 1 . rst $end
$var reg 2 a q [1:0] $end
$upscope $end
$scope module OUTPUTS $end
$var wire 1 , clk $end
$var wire 4 b d [3:0] $end
$var wire 1 8 enable $end
$var wire 1 . rst $end
$var reg 4 c q [3:0] $end
$upscope $end
$scope module PHASE $end
$var wire 1 , clk $end
$var wire 1 d enable $end
$var wire 1 . rst $end
$var wire 1 $ q $end
$scope module ffd1 $end
$var wire 1 , clk $end
$var wire 1 e d $end
$var wire 1 d enable $end
$var wire 1 . rst $end
$var reg 1 $ q $end
$upscope $end
$upscope $end
$scope module PROGRAMCOUNTER $end
$var wire 1 , clk $end
$var wire 1 < enabled $end
$var wire 1 7 load $end
$var wire 12 f loadvalue [11:0] $end
$var wire 1 . rst $end
$var reg 12 g counter [11:0] $end
$upscope $end
$scope module RAM $end
$var wire 12 h address_RAM [11:0] $end
$var wire 1 = csRAM $end
$var wire 4 i data_bus [3:0] $end
$var wire 1 1 weRAM $end
$var reg 4 j data_out [3:0] $end
$upscope $end
$scope module ROM $end
$var wire 8 k data [7:0] $end
$var wire 12 l direccion [11:0] $end
$upscope $end
$upscope $end
$upscope $end
$enddefinitions $end
#0
$dumpvars
bx l
bx k
bx j
bx i
bx h
bx g
bx f
xe
1d
bx c
bx b
bx a
bx `
bx _
bx ^
bx ]
bx \
bx [
bx Z
bx Y
xX
bx W
bx V
bx U
bx T
bx S
bx R
b110 Q
bx P
bx O
bx N
bx M
bx L
bx K
bx J
bx I
bx H
bx G
xF
bx E
bx D
xC
xB
xA
x@
bx ?
bx >
x=
x<
bx ;
x:
x9
x8
x7
x6
x5
x4
bx 3
bx 2
x1
b110 0
bx /
0.
b110 -
0,
bx +
bx *
bx )
bx (
x'
bx &
bx %
x$
bx #
x"
bx !
$end
#2
b0 !
b0 /
b0 K
b0 P
b0 R
b0 S
b0 b
b0 i
08
04
05
16
01
0=
0C
0B
b0 L
0A
09
0:
07
1<
b1000000001000 V
b1000000001000 W
1@
b0 G
b0 H
b0 M
b0 O
b1 `
0F
1e
1X
b0 N
0"
0'
b0 &
b0 ;
b0 Y
b0 ]
b0 %
b0 3
b0 T
b0 Z
b0 _
b0 U
0$
b0 )
b0 ?
b0 I
b0 J
b0 a
b0 +
b0 E
b0 c
b1111 ^
b100 \
b1001111 (
b1001111 >
b1001111 f
b1001111 h
b1001111 #
b1001111 2
b1001111 [
b1001111 k
b0 *
b0 D
b0 g
b0 l
1.
#3
0.
#5
b0 `
0@
b1111 G
b1111 H
b1111 M
b1111 O
b1111 N
b1111 !
b1111 /
b1111 K
b1111 P
b1111 R
b1111 S
b1111 b
b1111 i
14
06
b10 L
1B
19
1:
0<
b11010000010 V
b11010000010 W
0e
0X
1$
b1111 %
b1111 3
b1111 T
b1111 Z
b1111 _
b100001 U
b100 &
b100 ;
b100 Y
b100 ]
b1101 \
b111111011111 (
b111111011111 >
b111111011111 f
b111111011111 h
b11011111 #
b11011111 2
b11011111 [
b11011111 k
b1 *
b1 D
b1 g
b1 l
1,
#10
0,
#15
04
16
b0 L
0B
09
0:
1<
b1000000001000 V
b1000000001000 W
1e
1X
b100000 U
0$
b1111 )
b1111 ?
b1111 I
b1111 J
1,
#20
0,
#25
18
0<
b1001 V
b1001 W
0e
0X
1$
b1101001 U
b1101 &
b1101 ;
b1101 Y
b1101 ]
b1 ^
b101 \
b111101010001 (
b111101010001 >
b111101010001 f
b111101010001 h
b1010001 #
b1010001 2
b1010001 [
b1010001 k
b10 *
b10 D
b10 g
b10 l
1,
#30
0,
#35
08
1<
b1000000001000 V
b1000000001000 W
1e
1X
b1101000 U
0$
b1111 +
b1111 E
b1111 c
1,
#40
0,
#45
b110 G
b110 H
b110 M
b110 O
b110 N
b110 !
b110 /
b110 K
b110 P
b110 R
b110 S
b110 b
b110 i
15
06
b10 L
1B
19
1:
0<
b11010000100 V
b11010000100 W
0e
0X
1$
b1 %
b1 3
b1 T
b1 Z
b1 _
b101001 U
b101 &
b101 ;
b101 Y
b101 ]
b0 ^
b100 \
b101000000 (
b101000000 >
b101000000 f
b101000000 h
b1000000 #
b1000000 2
b1000000 [
b1000000 k
b11 *
b11 D
b11 g
b11 l
1,
#50
0,
#55
05
16
b0 L
0B
09
0:
1<
b1000000001000 V
b1000000001000 W
1e
1X
b101000 U
0$
b110 )
b110 ?
b110 I
b110 J
1,
#60
0,
#65
b1 `
1@
b0 G
b0 H
b0 M
b0 O
b0 N
b0 !
b0 /
b0 K
b0 P
b0 R
b0 S
b0 b
b0 i
14
06
b10 L
1B
19
1:
0<
b11010000010 V
b11010000010 W
0e
0X
1$
b0 %
b0 3
b0 T
b0 Z
b0 _
b100001 U
b100 &
b100 ;
b100 Y
b100 ]
b1111 ^
b1001111 (
b1001111 >
b1001111 f
b1001111 h
b1001111 #
b1001111 2
b1001111 [
b1001111 k
b100 *
b100 D
b100 g
b100 l
1,
#70
0,
#75
04
16
b0 L
0B
09
0:
1<
b1000000001000 V
b1000000001000 W
1e
1X
1"
b100010 U
0$
b0 )
b0 ?
b0 I
b0 J
b1 a
1,
#80
0,
#85
b0 `
0@
b1111 G
b1111 H
b1111 M
b1111 O
b1111 N
b1111 !
b1111 /
b1111 K
b1111 P
b1111 R
b1111 S
b1111 b
b1111 i
14
06
b10 L
1B
19
1:
0<
b11010000010 V
b11010000010 W
0e
0X
b100011 U
1$
b1111 %
b1111 3
b1111 T
b1111 Z
b1111 _
b1010 ^
b1010 \
b111110101010 (
b111110101010 >
b111110101010 f
b111110101010 h
b10101010 #
b10101010 2
b10101010 [
b10101010 k
b101 *
b101 D
b101 g
b101 l
1,
#90
0,
#95
04
16
b0 L
0B
09
0:
1<
b1000000001000 V
b1000000001000 W
1e
1X
0"
b100000 U
0$
b1111 )
b1111 ?
b1111 I
b1111 J
b0 a
1,
#100
0,
#105
b1001 G
b1001 H
b1001 M
b1001 O
b10 `
1F
b1010 !
b1010 /
b1010 K
b1010 P
b1010 R
b1010 S
b1010 b
b1010 i
b11001 N
14
06
1C
b11 L
1B
19
1:
0<
b11011000010 V
b11011000010 W
0e
0X
1$
b1010 %
b1010 3
b1010 T
b1010 Z
b1010 _
b1010001 U
b1010 &
b1010 ;
b1010 Y
b1010 ]
b1000 ^
b10 \
b101000101000 (
b101000101000 >
b101000101000 f
b101000101000 h
b101000 #
b101000 2
b101000 [
b101000 k
b110 *
b110 D
b110 g
b110 l
1,
#110
0,
#115
b0 `
0F
b1001 !
b1001 /
b1001 K
b1001 P
b1001 R
b1001 S
b1001 b
b1001 i
04
16
0C
b0 L
0B
09
0:
1<
b1000000001000 V
b1000000001000 W
b1001 G
b1001 H
b1001 M
b1001 O
1e
1X
b1001 N
1'
b1010100 U
0$
b1001 )
b1001 ?
b1001 I
b1001 J
b10 a
1,
#120
0,
#125
b1 G
b1 H
b1 M
b1 O
b1000 !
b1000 /
b1000 K
b1000 P
b1000 R
b1000 S
b1000 b
b1000 i
b1 N
14
06
b1 L
1C
19
0<
b1001000010 V
b1001000010 W
0e
0X
1$
b1000 %
b1000 3
b1000 T
b1000 Z
b1000 _
b10101 U
b10 &
b10 ;
b10 Y
b10 ]
b1010 ^
b100 \
b100001001010 (
b100001001010 >
b100001001010 f
b100001001010 h
b1001010 #
b1001010 2
b1001010 [
b1001010 k
b111 *
b111 D
b111 g
b111 l
1,
#130
0,
#135
b1001 G
b1001 H
b1001 M
b1001 O
b1001 !
b1001 /
b1001 K
b1001 P
b1001 R
b1001 S
b1001 b
b1001 i
b1001 N
04
16
b0 L
0C
09
1<
b1000000001000 V
b1000000001000 W
1e
1X
0'
b10000 U
0$
b0 a
1,
#140
0,
#145
b1010 G
b1010 H
b1010 M
b1010 O
b1010 N
b1010 !
b1010 /
b1010 K
b1010 P
b1010 R
b1010 S
b1010 b
b1010 i
14
06
b10 L
1B
19
1:
0<
b11010000010 V
b11010000010 W
0e
0X
1$
b1010 %
b1010 3
b1010 T
b1010 Z
b1010 _
b100001 U
b100 &
b100 ;
b100 Y
b100 ]
b1100 ^
b10 \
b101000101100 (
b101000101100 >
b101000101100 f
b101000101100 h
b101100 #
b101100 2
b101100 [
b101100 k
b1000 *
b1000 D
b1000 g
b1000 l
1,
#150
0,
#155
04
16
b0 L
0B
09
0:
1<
b1000000001000 V
b1000000001000 W
1e
1X
b100000 U
0$
b1010 )
b1010 ?
b1010 I
b1010 J
1,
#160
0,
#165
b10 `
1F
b1110 G
b1110 H
b1110 M
b1110 O
b1100 !
b1100 /
b1100 K
b1100 P
b1100 R
b1100 S
b1100 b
b1100 i
b11110 N
14
06
b1 L
1C
19
0<
b1001000010 V
b1001000010 W
0e
0X
1$
b1100 %
b1100 3
b1100 T
b1100 Z
b1100 _
b10001 U
b10 &
b10 ;
b10 Y
b10 ]
b1 ^
b1010 \
b110010100001 (
b110010100001 >
b110010100001 f
b110010100001 h
b10100001 #
b10100001 2
b10100001 [
b10100001 k
b1001 *
b1001 D
b1001 g
b1001 l
1,
#170
0,
#175
b1010 G
b1010 H
b1010 M
b1010 O
b0 `
0F
b1010 !
b1010 /
b1010 K
b1010 P
b1010 R
b1010 S
b1010 b
b1010 i
b1010 N
04
16
b0 L
0C
09
1<
b1000000001000 V
b1000000001000 W
1e
1X
1'
b10100 U
0$
b10 a
1,
#180
0,
#185
b1011 G
b1011 H
b1011 M
b1011 O
b0 `
0F
b1 !
b1 /
b1 K
b1 P
b1 R
b1 S
b1 b
b1 i
b1011 N
14
06
1C
b11 L
1B
19
1:
0<
b11011000010 V
b11011000010 W
0e
0X
1$
b1 %
b1 3
b1 T
b1 Z
b1 _
b1010101 U
b1010 &
b1010 ;
b1010 Y
b1010 ]
b1011 ^
b1110 \
b111101011 (
b111101011 >
b111101011 f
b111101011 h
b11101011 #
b11101011 2
b11101011 [
b11101011 k
b1010 *
b1010 D
b1010 g
b1010 l
1,
#190
0,
#195
b1011 !
b1011 /
b1011 K
b1011 P
b1011 R
b1011 S
b1011 b
b1011 i
04
16
0C
b0 L
0B
09
0:
1<
b1000000001000 V
b1000000001000 W
b1011 G
b1011 H
b1011 M
b1011 O
1e
1X
b1011 N
0'
b1010000 U
0$
b1011 )
b1011 ?
b1011 I
b1011 J
b0 a
1,
#200
0,
#205
b100 G
b100 H
b100 M
b100 O
b1011 !
b1011 /
b1011 K
b1011 P
b1011 R
b1011 S
b1011 b
b1011 i
b100 N
14
06
b100 L
1A
19
1:
0<
b11100000010 V
b11100000010 W
0e
0X
1$
b1011 %
b1011 3
b1011 T
b1011 Z
b1011 _
b1110001 U
b1110 &
b1110 ;
b1110 Y
b1110 ]
b0 ^
b1101 \
b101111010000 (
b101111010000 >
b101111010000 f
b101111010000 h
b11010000 #
b11010000 2
b11010000 [
b11010000 k
b1011 *
b1011 D
b1011 g
b1011 l
1,
#210
0,
#215
b100 !
b100 /
b100 K
b100 P
b100 R
b100 S
b100 b
b100 i
04
16
b0 L
0A
09
0:
1<
b1000000001000 V
b1000000001000 W
b100 G
b100 H
b100 M
b100 O
1e
1X
b100 N
b1110000 U
0$
b100 )
b100 ?
b100 I
b100 J
1,
#220
0,
#225
18
0<
b1001 V
b1001 W
0e
0X
1$
b0 %
b0 3
b0 T
b0 Z
b0 _
b1101001 U
b1101 &
b1101 ;
b1101 Y
b1101 ]
b101 \
b1010000 (
b1010000 >
b1010000 f
b1010000 h
b1010000 #
b1010000 2
b1010000 [
b1010000 k
b1100 *
b1100 D
b1100 g
b1100 l
1,
#230
0,
#235
08
1<
b1000000001000 V
b1000000001000 W
1e
1X
b1101000 U
0$
b100 +
b100 E
b100 c
1,
#240
0,
#245
b110 G
b110 H
b110 M
b110 O
b110 N
b110 !
b110 /
b110 K
b110 P
b110 R
b110 S
b110 b
b110 i
15
06
b10 L
1B
19
1:
0<
b11010000100 V
b11010000100 W
0e
0X
1$
b101001 U
b101 &
b101 ;
b101 Y
b101 ]
b111 \
b1110000 (
b1110000 >
b1110000 f
b1110000 h
b1110000 #
b1110000 2
b1110000 [
b1110000 k
b1101 *
b1101 D
b1101 g
b1101 l
1,
#250
0,
#255
05
16
b0 L
0B
09
0:
1<
b1000000001000 V
b1000000001000 W
1e
1X
b101000 U
0$
b110 )
b110 ?
b110 I
b110 J
1,
#260
0,
#265
11
1=
b1000000111000 V
b1000000111000 W
0e
0X
1$
b111001 U
b111 &
b111 ;
b111 Y
b111 ]
b0 \
b0 (
b0 >
b0 f
b0 h
b0 #
b0 2
b0 [
b0 k
b1110 *
b1110 D
b1110 g
b1110 l
1,
#270
0,
#275
01
0=
b1000000001000 V
b1000000001000 W
1e
1X
b111000 U
0$
b1111 ^
b100 \
b1001111 (
b1001111 >
b1001111 f
b1001111 h
b1001111 #
b1001111 2
b1001111 [
b1001111 k
b1111 *
b1111 D
b1111 g
b1111 l
1,
#280
0,
