proyecto/verilog/proyecto.v
//José Alejandro Rodríguez Porras 19131
//Electrónica Digital
//Proyecto FSM
//Caja de velocidades automática con modo carrera
//Módulo Flip Flop Tipo D con reset asíncrono de un bit
//José Alejandro Rodríguez Porras 19131
//Electrónica Digital
//Proyecto FSM
//Caja de velocidades automática optimizada con modo carrera
//Módulo Flip Flop Tipo D con reset asíncrono de dos bits
module dff2(input clk, rst, input [1:0]d, output reg [1:0]q);

    always @ (posedge clk or posedge rst)
        if (rst)
            q <= 2'b00; 
    else begin
            q <= d;
    end
endmodule
// Módulo Flip Flop Tipo D con reset asíncrono de cuatro bits
module dff4(input clk, rst, input [3:0]d, output reg [3:0]q);

    always @ (posedge clk or posedge rst)
        if (rst)
            q <= 4'b0000;
    else begin
            q <= d;
    end
endmodule

//FSM modo carrera
module MC(input wire clk, rst, SV, RF, TM, SC, E, input wire [1:0]SP, output wire D, A, output wire [1:0]S, output wire [1:0]SF);
    
    //Ecuaciones de estados futuros
    assign SF[1] = (~S[1] & ~S[0] & ~RF & SV & TM & E) | (~S[1] & ~S[0] & ~RF & SV & SC & E) | (S[1] & ~S[0] & SV & TM & ~SP[1] & E) | (S[1] & ~S[0] & SV & SC & ~SP[1] & E) | 
    (S[1] & ~S[0] & SV & TM & ~SP[0] & E) | (S[1] & ~S[0] & SV & SC & ~SP[0] & E);

    assign SF[0] = (~S[1] & S[0] & ~TM & ~SC & E) | (~S[1] & RF & ~SC & ~TM & ~SC & E) | (~S[1] & ~TM & ~SC & ~SP[1] & ~S[0] & E) | (~S[1] & ~TM & ~SC & SP[1] & ~SP[0] & E);
  
   
    dff2 FF2(clk, rst, SF, S);  
   //Ecuaciones de salidas
    assign D = (S[1] & ~S[0]);
    assign A = (~S[1] & S[0]);

endmodule
//FSM Principal, Caja de 6 Velocidades de cambio automático para vehículo (1a, 2a, 3a, 4a, 5a, 6a)
module C_Velocidad(input wire clk, rst, A, AM, D, DM, TD, T1, T2, T3, T4, T5, output wire [3:0]S, output wire [3:0]SF, output wire [2:0]VA, output wire [2:0]ET, output wire SV, ETD);
    
    //Ecuaciones de estados futuros
    assign SF[3] = (S[3] & ~S[2] & S[0]) | (S[3] & S[2] & ~S[1] & ~S[0]) | (S[3] & ~S[2] & S[1] & A) | (S[3] & ~S[2] & S[1] & AM) | (S[3] & ~S[2] & S[1] & ~D & ~DM) | 
    (~S[3] & S[2] & S[1] & S[0] & ~A & ~AM & D) | (~S[3] & S[2] & S[1] & S[0] & ~A & ~AM & DM) | (~S[3] & S[2] & S[1] & S[0] & A & ~D & ~DM) | (~S[3] & S[2] & S[1] & S[0] & AM & ~D & ~DM) | 
    (S[3] & ~S[1] & ~S[0] & A & ~D & ~DM) | (S[3] & ~S[1] & ~S[0] & AM & ~D & ~DM) | (S[3] & ~S[2] & ~A & ~AM & D & ~TD) | (S[3] & ~S[2] & ~A & ~AM & DM & ~TD);

    assign SF[2] = (~S[3] & S[2] & ~S[1] & S[0]) | (S[3] & ~S[2] & ~S[1] & ~S[0] & A & D) | (S[3] & ~S[2] & ~S[1] & ~S[0] & AM & D) | (~S[2] & S[1] & S[0] & ~A & ~AM & D) |
    (S[3] & ~S[2] & ~S[1] & ~S[0] & A & DM) | (S[3] & ~S[2] & ~S[1] & ~S[0] & AM & DM) | (~S[2] & S[1] & S[0] & ~A & ~AM & DM) | (~S[2] & S[1] & S[0] & A & ~D & ~DM) | 
    (~S[2] & S[1] & S[0] & AM & ~D & ~DM) | (S[2] & ~S[1] & ~S[0] & ~A & ~AM & D & ~TD) | (S[2] & ~S[1] & ~S[0] & ~A & ~AM & DM & ~TD) | (S[3] & ~S[2] & ~S[1] & ~S[0] & ~A & ~AM & ~D & ~DM) | 
    (~S[3] & S[2] & S[1] & A & D) | (~S[3] & S[2] & S[1] & AM & D) | (~S[3] & S[2] & S[1] & A & DM) | (~S[3] & S[2] & S[1] & AM & DM) | (~S[3] & S[2] & S[1] & ~S[0] & ~TD) | 
    (~S[3] & S[2] & ~S[0] & A & ~D & ~DM) | (~S[3] & S[2] & ~S[0] & AM & ~D & ~DM) | (~S[3] & S[2] & S[1] & ~A & ~AM & ~D & ~DM) | (S[3] & ~S[2] & ~S[0] & ~A & ~AM & D & TD) | 
    (S[3] & ~S[2] & ~S[0] & ~A & ~AM & DM & TD); 
  
    assign SF[1] = (~S[3] & S[1] & S[0] & A & D) | (~S[2] & S[1] & S[0] & A & D) | (S[3] & ~S[1] & ~S[0] & A & D) | (S[2] & ~S[1] & ~S[0] & A & D) | (~S[3] & S[1] & S[0] & AM & D) |
    (~S[2] & S[1] & S[0] & AM & D) | (S[3] & ~S[1] & ~S[0] & AM & D) | (S[2] & ~S[1] & ~S[0] & AM & D) | (~S[3] & S[1] & S[0] & A & DM) | (~S[2] & S[1] & S[0] & A & DM) |
    (S[3] & ~S[1] & ~S[0] & A & DM) | (S[2] & ~S[1] & ~S[0] & A & DM) | (~S[3] & S[1] & S[0] & AM & DM) | (~S[2] & S[1] & S[0] & AM & DM) | (S[3] & ~S[1] & ~S[0] & AM & DM) |
    (S[2] & ~S[1] & ~S[0] & AM & DM) | (~S[3] & ~S[1] & S[0] & ~A & ~AM & D) | (~S[2] & ~S[1] & S[0] & ~A & ~AM & D) | (~S[3] & ~S[1] & S[0] & ~A & ~AM & DM) | (~S[2] & ~S[1] & S[0] & ~A & ~AM & DM) |
    (~S[3] & ~S[1] & S[0] & A & ~D & ~DM) | (~S[2] & ~S[1] & S[0] & A & ~D & ~DM) | (~S[3] & S[1] & ~S[0] & A & ~D & ~DM) | (~S[2] & S[1] & ~S[0] & A & ~D & ~DM) | (~S[3] & ~S[1] & S[0] & AM & ~D & ~DM) |
    (~S[2] & ~S[1] & S[0] & AM & ~D & ~DM) | (~S[3] & S[1] & ~S[0] & AM & ~D & ~DM) | (~S[2] & S[1] & ~S[0] & AM & ~D & ~DM) | (~S[3] & S[2] & S[1] & ~S[0] & ~A & ~AM & D) |
    (S[3] & ~S[2] & S[1] & ~S[0] & ~A & ~AM & D) | (~S[3] & S[2] & S[1] & ~S[0] & ~A & ~AM & DM) | (S[3] & ~S[2] & S[1] & ~S[0] & ~A & ~AM & DM) | (~S[3] & S[1] & S[0] & ~A & ~AM & ~D & ~DM) |
    (~S[2] & S[1] & S[0] & ~A & ~AM & ~D & ~DM) | (S[3] & ~S[1] & ~S[0] & ~A & ~AM & ~D & ~DM) | (S[2] & ~S[1] & ~S[0] & ~A & ~AM & ~D & ~DM) | (S[3] & S[2] & ~S[1] & ~S[0] & ~D & ~DM) |
    (~S[2] & S[1] & ~S[0] & ~A & ~AM & D & ~TD) | (~S[2] & S[1] & ~S[0] & ~A & ~AM & DM & ~TD);
    
    assign SF[0] = (~S[3] & ~S[2] & ~S[1] & ~S[0] & A & ~D & ~DM) | (~S[3] & ~S[2] & ~S[1] & ~S[0] & AM & ~D & ~DM) | (~S[3] & S[2] & A & D) | (~S[2] & S[1] & A & D) | (~S[2] & S[0] & A & D) |
    (~S[3] & S[2] & AM & D) | (~S[2] & S[1] & AM & D) | (~S[2] & S[0] & AM & D) | (~S[3] & S[2] & A & DM) | (~S[2] & S[1] & A & DM) | (~S[2] & S[0] & A & DM) | (~S[3] & S[2] & AM & DM) | 
    (~S[2] & S[1] & AM & DM) | (~S[2] & S[0] & AM & DM) | (S[3] & ~S[1] & ~S[0] & A & D) | (S[3] & ~S[1] & ~S[0] & AM & D) | (S[3] & ~S[1] & ~S[0] & A & DM) | (S[3] & ~S[1] & ~S[0] & AM & DM) | 
    (S[3] & S[2] & ~S[1] & ~S[0] & ~D & ~DM) | (~S[3] & S[2] & ~A & ~AM & ~D & ~DM) | (S[3] & ~S[2] & ~A & ~AM & ~D & ~DM) | (~S[2] & S[1] & ~A & ~AM & ~D & ~DM) | (~S[2] & S[0] & ~A & ~AM & ~D & ~DM) | 
    (~S[3] & S[2] & ~S[0] & ~A & ~AM & TD) | (S[3] & ~S[2] & ~S[0] & ~A & ~AM & TD) | (S[2] & ~S[1] & ~S[0] & ~A & ~AM & TD) | (S[2] & ~S[1] & ~S[0] & ~D & ~DM & T2) | 
    (S[3] & ~S[1] & ~S[0] & ~D & ~DM & T4) | (~S[3] & ~S[2] & S[1] & ~S[0] & ~D & ~DM & T1) | (~S[3] & S[2] & S[1] & ~S[0] & ~D & ~DM & T3) | (S[3] & ~S[2] & S[1] & ~S[0] & ~D & ~DM & T5);


    dff4 FF4(clk, rst, SF, S);

    //Ecuaciones de salidas
    assign VA[2] = (S[3] & ~S[2]) | (S[3] & ~S[1] & ~S[0]) | (~S[3] & S[2] & S[1] & S[0]);
    assign VA[1] = (~S[3] & S[2] & ~S[1]) | (~S[2] & S[1] & S[0]) | (~S[3] & S[2] & ~S[0]) | (S[2] & ~S[1] & ~S[0]);
    assign VA[0] = (~S[3] & ~S[1] & S[0]) | (~S[2] & ~S[1] & S[0]) | (~S[3] & S[1] & ~S[0]) | (~S[2] & S[1] & ~S[0]);
    assign SV = (S[3] & ~S[2]) | (S[3] & ~S[1] & ~S[0]) | (~S[3] & S[2] & S[1] & S[0]);
    assign ETD = (~S[3] & S[2] & ~S[0]) | (~S[2] & S[1] & ~S[0]) | (S[3] & ~S[1] & ~S[0]);
    assign ET[2] = (S[3] & ~S[2] & ~S[0]) | (S[3] & ~S[1] & ~S[0]);
    assign ET[1] = (~S[3] & S[2] & ~S[0]);
    assign ET[0] = (~S[3] & S[1] & ~S[0]) | (~S[2] & S[1] & ~S[0]) | (S[3] & S[2] & ~S[1] & ~S[0]);

endmodule

//Módulo del decoder para el seleccionador de timers usando case
module decoder(input wire [2:0]ET, input enabledec, output reg [5:0]decoder_out); 

always @ (enabledec or ET)
begin
  decoder_out = 0;
  if (enabledec) begin
    case (ET)
      3'b000 : decoder_out <= 6'b000000;
      3'b001 : decoder_out <= 6'b000001;
      3'b010 : decoder_out <= 6'b000010;
      3'b011 : decoder_out <= 6'b000100;
      3'b100 : decoder_out <= 6'b001000;
      3'b101 : decoder_out <= 6'b010000;
    endcase
  end
end

endmodule

//Módulo de Seleccionador de timers 
module Seleccionador(input wire [2:0]ET, input wire EnD, output wire TimerLED1, output wire TimerLED2, output wire TimerLED3, output wire TimerLED4, output wire TimerLED5, output [5:0]dec);
    decoder DE(ET, EnD, dec);
    assign TimerLED1 = dec[0];
    assign TimerLED2 = dec[1];
    assign TimerLED3 = dec[2];
    assign TimerLED4 = dec[3];
    assign TimerLED5 = dec[4];
endmodule

//Módulo del timer para desacelerar
module Timer_desacelerar(input wire ETD, output reg TD);
    always @ (ETD) begin
        if (ETD == 0) begin
            TD = 0;
        end 
        while(ETD) begin
            #30 TD = 1;
            #10 TD = 0;    
        end
    end
endmodule

//Módulo del Timer 1 de aceleración en la 1a. velocidad con respectivo velocímetro 1
module Timer_a1(input wire TimerLED1, output reg T1, output reg [2:0]Vlm1);
    always @ (TimerLED1) begin
        if (TimerLED1 == 0) begin
            Vlm1 = 3'b000;
            T1 = 0;
        end 
        while(TimerLED1) begin   
            #10 Vlm1 = 3'b001;
            #10 Vlm1 = 3'b010;
            #10 Vlm1 = 3'b011; ; T1 = 1;
            #11 T1 = 0; Vlm1 = 3'b000;  
        end
    end
endmodule

//Módulo del Timer 2 de aceleración en la 2a. velocidad con respectivo velocímetro 2
module Timer_a2(input wire TimerLED2, output reg T2, output reg [2:0]Vlm2);
    always @ (TimerLED2) begin
        if (TimerLED2 == 0) begin
            Vlm2 = 3'b000;
            T2 = 0;
        end 
        while(TimerLED2) begin
            #10 Vlm2 = 3'b001;
            #10 Vlm2 = 3'b010;
            #10 Vlm2 = 3'b011;
            #10 Vlm2 = 3'b100; ; T2 = 1;
            #11 T2 = 0; Vlm2 = 3'b000;
        end
    end
endmodule

//Módulo del Timer 3 de aceleración en la 3a. velocidad con respectivo velocímetro 3
module Timer_a3(input wire TimerLED3, output reg T3, output reg [2:0]Vlm3);
    always @ (TimerLED3) begin
        if (TimerLED3 == 0) begin
            Vlm3 = 3'b000;
            T3 = 0;
        end 
        while(TimerLED3) begin
            #10 Vlm3 = 3'b001;
            #10 Vlm3 = 3'b010;
            #10 Vlm3 = 3'b011;
            #10 Vlm3 = 3'b100;
            #10 Vlm3 = 3'b101; ; T3 = 1;
            #11 T3 = 0; Vlm3 = 3'b000;  
        end
    end
endmodule
//Módulo del Timer 4 de aceleración en la 4a. velocidad con respectivo velocímetro 4
module Timer_a4(input wire TimerLED4, output reg T4, output reg [2:0]Vlm4);
    always @ (TimerLED4) begin
        if (TimerLED4 == 0) begin
                Vlm4 = 3'b000;
                T4 = 0;
        end 
        while(TimerLED4) begin
            #11 Vlm4 = 3'b001;
            #10 Vlm4 = 3'b010;
            #10 Vlm4 = 3'b011;
            #10 Vlm4 = 3'b100;
            #10 Vlm4 = 3'b101;
            #10 Vlm4 = 3'b110; ; T4 = 1;
            #11 T4 = 0; Vlm4 = 3'b000;  
        end
    end
endmodule
//Módulo del Timer 5 de aceleración con respectivo velocímetro 5 en la 5a. velocidad y en la 6a. velocidad
module Timer_a5(input wire TimerLED5, input wire [2:0]VA , output reg T5, output reg [3:0]Vlm5);
    always @ (TimerLED5) begin
        if (TimerLED5 == 0) begin
            Vlm5 = 4'b0000;
            T5 = 0;
        end 
        //Velocímetro 5 en 5a. velocidad
        while(TimerLED5 == 1 & VA == 3'b101) begin
            #11 Vlm5 = 4'b0001;
            #10 Vlm5 = 4'b0010;
            #10 Vlm5 = 4'b0011;
            #10 Vlm5 = 4'b0100;
            #10 Vlm5 = 4'b0101;
            #10 Vlm5 = 4'b0110;
            #10 Vlm5 = 4'b0111; ; T5 = 1;
            #10 T5 = 0; Vlm5 = 4'b0000;  
        end
        //Velocímetro 5 en 6a. velocidad
        while (TimerLED5 == 1 & VA == 3'b110) begin
            #10  Vlm5 = 4'b0001; T5 = 1; 
            #10 Vlm5 = 4'b0000; T5 = 0; 
        end
    end
endmodule

proyecto/verilog/proyecto_tb.v
//José Alejandro Rodríguez Porras 19131
//Electrónica Digital
//Proyecto FSM
//Caja de velocidades automática con modo carrera
module testbench();
    //Declaración de variables
    reg clk, rst, RF, TM, SC, E, DM, AM, EnD;
    wire SV, TD, A, D,  ETD, TimerLED1, TimerLED2, TimerLED3, TimerLED4, TimerLED5, T1, T2, T3, T4, T5;
    wire [2:0]Vlm1;
    wire [2:0]Vlm2;
    wire [2:0]Vlm3;
    wire [2:0]Vlm4;
    wire [3:0]Vlm5;
    wire [5:0]dec;
    reg [1:0]SP;
    wire [1:0]S_MC; 
    wire [1:0]SF_MC;
    wire [2:0]VA;
    wire [2:0]ET;
    wire [3:0]S_C_V;
    wire [3:0]SF_C_V;
    //Llamar módulos de modo carrera y caja de velocidades respectivamente
    MC MC_FSM(clk, rst, SV, RF, TM, SC, E, SP, D, A, S_MC, SF_MC);
    C_Velocidad C_V_FSM(clk, rst, A, AM, D, DM, TD, T1, T2, T3, T4, T5, S_C_V, SF_C_V, VA, ET, SV, ETD);
    //Llamar a los módulos de decoder, timers y velocímetros para interpretar las salidas de la caja de velocidades
    Seleccionador SEL(ET, EnD, TimerLED1, TimerLED2, TimerLED3, TimerLED4, TimerLED5, dec);
    Timer_desacelerar T_DES(ETD, TD);
    Timer_a1 TA1(TimerLED1, T1, Vlm1);
    Timer_a2 TA2(TimerLED2, T2, Vlm2);
    Timer_a3 TA3(TimerLED3, T3, Vlm3);
    Timer_a4 TA4(TimerLED4, T4, Vlm4);
    Timer_a5 TA5(TimerLED5, VA, T5, Vlm5);
     initial begin
    #1 $display("RF TM SC SP E AM DM | VA  SV  ETD TimerLED1 TimerLED2 TimerLED3 TimerLED4 TimerLED5   Vlm1     Vlm2  Vlm3  Vlm4   Vlm5");
    $display("--------------------|----------------------------------------------------------------------------------------------------");
    $monitor("%b   %b  %b %b %b %b  %b  | %b  %b   %b      %b         %b         %b          %b           %b     %b      %b   %b   %b    %b", RF, TM, SC, SP, E, AM, DM, VA, SV, ETD, 
    TimerLED1, TimerLED2, TimerLED3, TimerLED4, TimerLED5, Vlm1, Vlm2, Vlm3, Vlm4, Vlm5);

     EnD = 1; clk = 0; rst = 1;  RF = 0; TM = 0; SC = 0; SP = 2'b00; E = 0; AM = 0;  DM = 0; 
    #1   rst = 1;
    #1   rst = 0;
    // Demostración de que el carro puede cambia de velocidades automáticamente al mantener el 
    //acelerador presionado (recorrido por cada una de las 6 velocidades)
    #2   RF = 0; TM = 0; SC = 0; SP = 2'b00; E = 0; AM = 1; DM = 0;
    //Demostración de que el carro permanece a velocidad constante y no cambia de velocidad en la caja
    //de velocidades al no presionar ni el acelerador o desacelerador manual
    #409 RF = 0; TM = 0; SC = 0; SP = 2'b00; E = 0; AM = 0; DM = 0;
    //Prueba de uso del desacelerador manual a través de las 6 velocidades (6a a 1a)
    #35  RF = 0; TM = 0; SC = 0; SP = 2'b00; E = 0; AM = 0; DM = 1;
    #295 RF = 0; TM = 0; SC = 0; SP = 2'b00; E = 0; AM = 0; DM = 0;
    #40  RF = 0; TM = 0; SC = 0; SP = 2'b00; E = 0; AM = 1; DM = 0;
    //Prueba de que el carro se puede quedar en una velocidad constante en cualquier velocidad
    //si no se presiona ni el acelerador o el desacelerador
    #160 RF = 0; TM = 0; SC = 0; SP = 2'b00; E = 0; AM = 0; DM = 0;
    //Prueba de que si se presionan el acelerador y el desacelerador manual de forma simultánea
    //el vehículo no cambiará de la velocidad actual 
    #40  RF = 0; TM = 0; SC = 0; SP = 2'b00; E = 0; AM = 1; DM = 0;
    #69  RF = 0; TM = 0; SC = 0; SP = 2'b00; E = 0; AM = 1; DM = 1;
    //Prueba de que si se estaba presionando el desacelerador manual y se presiona el acelerador
    //manual a la vez el vehículo deja de cambiar de velocidad y se queda en la última velocidad utilizada
    #40  RF = 0; TM = 0; SC = 0; SP = 2'b00; E = 0; AM = 0; DM = 1;
    #70  RF = 0; TM = 0; SC = 0; SP = 2'b00; E = 0; AM = 1; DM = 1;
    #70  RF = 0; TM = 0; SC = 0; SP = 2'b00; E = 0; AM = 0; DM = 0;
    //Prueba de que si se deja de desacelerar manualmente el vehículo permanece en la velocidad actual
    #30  RF = 0; TM = 0; SC = 0; SP = 2'b00; E = 0; AM = 0; DM = 1;
    #50  RF = 0; TM = 0; SC = 0; SP = 2'b00; E = 0; AM = 0; DM = 0;
    //Prueba de que el reset funciona como freno de mano, es decir estaciona el carro 
    //desde cualquier velocidad que es esté usando, es decir lo pone en velocidad 0 (estacionado)
    #150  RF = 0; TM = 0; SC = 0; SP = 2'b00; E = 0; AM = 1; DM = 0;
    #100 rst = 1; AM = 0;
    #1   rst = 0;
    #39  RF = 0; TM = 0; SC = 0; SP = 2'b00; E = 0; AM = 0; DM = 0;
    //Prueba de que al activar el enable la caja de velocidades se puede controlar
    // por medio de sensores que activan el acelerador o desacelerador automático
    
    // el carro arranca al identificar un carro a su lado o delantera
    #10  RF = 0; TM = 0; SC = 0; SP = 2'b00; E = 1; AM = 0; DM = 0;
    #10  RF = 0; TM = 0; SC = 0; SP = 2'b01; E = 1; AM = 0; DM = 0;
    // Evidencia de que el vehículo procura acelerar automáticamente independientemente
    // de si hay carros o no alrededor, y cuando no se encienden sensores críticos (SC, TM)
    // o desacelerador manual
    #40  RF = 0; TM = 0; SC = 0; SP = 2'b00; E = 1; AM = 0; DM = 0;
    #100 RF = 0; TM = 0; SC = 0; SP = 2'b10; E = 1; AM = 0; DM = 0;
    #100 RF = 0; TM = 0; SC = 0; SP = 2'b10; E = 1; AM = 0; DM = 0;
    #100 RF = 0; TM = 0; SC = 0; SP = 2'b11; E = 1; AM = 0; DM = 0;
    #100 RF = 0; TM = 0; SC = 0; SP = 2'b00; E = 1; AM = 0; DM = 0;
    //Prueba de que si se enciende un sensor crítico (SC, TM) el carro comienza a desacelerar automáticamente
    #300 RF = 0; TM = 1; SC = 0; SP = 2'b00; E = 1; AM = 0; DM = 0;
    #200 RF = 0; TM = 0; SC = 0; SP = 2'b00; E = 1; AM = 0; DM = 0;
    #80  RF = 0; TM = 0; SC = 0; SP = 2'b00; E = 1; AM = 0; DM = 0;
    //Prueba de que si se presiona el acelerador manual mientras un sensor crítico está 
    //encendido, el vehículo se mantendrá a velocidad constante
    #10  RF = 0; TM = 1; SC = 0; SP = 2'b00; E = 1; AM = 1; DM = 0;
    //Prueba de que si se presiona el desacelerador manual mientras un sensor crítico encendido
    //está activando el desacelerador automático el vehículo desacelera normalmente, y si llega a 3a. el 
    //vehículo continuará desacelerando.
    #100 RF = 0; TM = 1; SC = 0; SP = 2'b00; E = 1; AM = 0; DM = 1;
    #100 RF = 0; TM = 0; SC = 0; SP = 2'b10; E = 1; AM = 0; DM = 0;
    //Prueba del sensor de recta final en el vehículo
    #100 RF = 1; TM = 0; SC = 0; SP = 2'b00; E = 1; AM = 0; DM = 0;
    //Prueba del sensor de recta final junto con el sensor TM (motor caliente)
    #60  RF = 1; TM = 1; SC = 0; SP = 2'b00; E = 1; AM = 0; DM = 0;
    //Prueba del sensor de recta final junto con el sensor SC (Sensor curvas)
    #100 RF = 1; TM = 0; SC = 1; SP = 2'b00; E = 1; AM = 0; DM = 0;
    //Prueba de que con el enable E apagado la máquina de sensores deja de controlar el acelerador y desacelerador automático del vehículo 
    // volviendo a controlar el vehículo con el acelerador y desacelerador manual 
    #100 RF = 1; TM = 0; SC = 0; SP = 2'b10; E = 0; AM = 0; DM = 0;
    #100 RF = 1; TM = 1; SC = 1; SP = 2'b10; E = 0; AM = 0; DM = 1;
    #50  RF = 0; TM = 0; SC = 1; SP = 2'b10; E = 0; AM = 0; DM = 0;
    #50  RF = 0; TM = 0; SC = 1; SP = 2'b10; E = 0; AM = 0; DM = 0;
    #50  RF = 0; TM = 0; SC = 0; SP = 2'b10; E = 1; AM = 0; DM = 0;
    // Prueba de que si se enciende el sensor crítico de curvas y hay un carro atrás
    // del vehículo, el desacelerador automático se queda intermintente, es decir
    // no cambiará a una velocidad menor para prevenir un choque
    #160 RF = 0; TM = 0; SC = 1; SP = 2'b11; E = 1; AM = 0; DM = 0;
    #100 RF = 0; TM = 0; SC = 1; SP = 2'b00; E = 1; AM = 0; DM = 0;
    #100 rst = 1; 
    #1 rst = 0;
    #300 $finish;
     end
    always
        #5 clk = ~clk;
        //creación del archivo vcd
    initial begin
        $dumpfile("proyecto_tb.vcd");
        $dumpvars(0,testbench);
    end
endmodule

proyecto/verilog/proyecto_tb.vcd
$date
	Sat Oct 17 16:22:06 2020
$end
$version
	Icarus Verilog
$end
$timescale
	1ps
$end
$scope module testbench $end
$var wire 6 ! dec [5:0] $end
$var wire 4 " Vlm5 [3:0] $end
$var wire 3 # Vlm4 [2:0] $end
$var wire 3 $ Vlm3 [2:0] $end
$var wire 3 % Vlm2 [2:0] $end
$var wire 3 & Vlm1 [2:0] $end
$var wire 3 ' VA [2:0] $end
$var wire 1 ( TimerLED5 $end
$var wire 1 ) TimerLED4 $end
$var wire 1 * TimerLED3 $end
$var wire 1 + TimerLED2 $end
$var wire 1 , TimerLED1 $end
$var wire 1 - TD $end
$var wire 1 . T5 $end
$var wire 1 / T4 $end
$var wire 1 0 T3 $end
$var wire 1 1 T2 $end
$var wire 1 2 T1 $end
$var wire 2 3 S_MC [1:0] $end
$var wire 4 4 S_C_V [3:0] $end
$var wire 1 5 SV $end
$var wire 2 6 SF_MC [1:0] $end
$var wire 4 7 SF_C_V [3:0] $end
$var wire 1 8 ETD $end
$var wire 3 9 ET [2:0] $end
$var wire 1 : D $end
$var wire 1 ; A $end
$var reg 1 < AM $end
$var reg 1 = DM $end
$var reg 1 > E $end
$var reg 1 ? EnD $end
$var reg 1 @ RF $end
$var reg 1 A SC $end
$var reg 2 B SP [1:0] $end
$var reg 1 C TM $end
$var reg 1 D clk $end
$var reg 1 E rst $end
$scope module C_V_FSM $end
$var wire 1 < AM $end
$var wire 1 = DM $end
$var wire 1 8 ETD $end
$var wire 1 5 SV $end
$var wire 1 D clk $end
$var wire 1 E rst $end
$var wire 3 F VA [2:0] $end
$var wire 1 - TD $end
$var wire 1 . T5 $end
$var wire 1 / T4 $end
$var wire 1 0 T3 $end
$var wire 1 1 T2 $end
$var wire 1 2 T1 $end
$var wire 4 G SF [3:0] $end
$var wire 4 H S [3:0] $end
$var wire 3 I ET [2:0] $end
$var wire 1 : D $end
$var wire 1 ; A $end
$scope module FF4 $end
$var wire 1 D clk $end
$var wire 4 J d [3:0] $end
$var wire 1 E rst $end
$var reg 4 K q [3:0] $end
$upscope $end
$upscope $end
$scope module MC_FSM $end
$var wire 1 ; A $end
$var wire 1 : D $end
$var wire 1 > E $end
$var wire 1 @ RF $end
$var wire 1 A SC $end
$var wire 2 L SP [1:0] $end
$var wire 1 5 SV $end
$var wire 1 C TM $end
$var wire 1 D clk $end
$var wire 1 E rst $end
$var wire 2 M SF [1:0] $end
$var wire 2 N S [1:0] $end
$scope module FF2 $end
$var wire 1 D clk $end
$var wire 2 O d [1:0] $end
$var wire 1 E rst $end
$var reg 2 P q [1:0] $end
$upscope $end
$upscope $end
$scope module SEL $end
$var wire 3 Q ET [2:0] $end
$var wire 1 ? EnD $end
$var wire 6 R dec [5:0] $end
$var wire 1 ( TimerLED5 $end
$var wire 1 ) TimerLED4 $end
$var wire 1 * TimerLED3 $end
$var wire 1 + TimerLED2 $end
$var wire 1 , TimerLED1 $end
$scope module DE $end
$var wire 3 S ET [2:0] $end
$var wire 1 ? enabledec $end
$var reg 6 T decoder_out [5:0] $end
$upscope $end
$upscope $end
$scope module TA1 $end
$var wire 1 , TimerLED1 $end
$var reg 1 2 T1 $end
$var reg 3 U Vlm1 [2:0] $end
$upscope $end
$scope module TA2 $end
$var wire 1 + TimerLED2 $end
$var reg 1 1 T2 $end
$var reg 3 V Vlm2 [2:0] $end
$upscope $end
$scope module TA3 $end
$var wire 1 * TimerLED3 $end
$var reg 1 0 T3 $end
$var reg 3 W Vlm3 [2:0] $end
$upscope $end
$scope module TA4 $end
$var wire 1 ) TimerLED4 $end
$var reg 1 / T4 $end
$var reg 3 X Vlm4 [2:0] $end
$upscope $end
$scope module TA5 $end
$var wire 1 ( TimerLED5 $end
$var wire 3 Y VA [2:0] $end
$var reg 1 . T5 $end
$var reg 4 Z Vlm5 [3:0] $end
$upscope $end
$scope module T_DES $end
$var wire 1 8 ETD $end
$var reg 1 - TD $end
$upscope $end
$upscope $end
$enddefinitions $end
#0
$dumpvars
bx Z
bx Y
bx X
bx W
bx V
bx U
bx T
bx S
bx R
bx Q
bx P
bx O
bx N
bx M
bx L
bx K
bx J
bx I
bx H
bx G
bx F
xE
xD
xC
bx B
xA
x@
x?
x>
x=
x<
x;
x:
bx 9
x8
bx 7
bx 6
x5
bx 4
bx 3
x2
x1
x0
x/
x.
x-
x,
x+
x*
x)
x(
bx '
bx &
bx %
bx $
bx #
bx "
bx !
$end
#1
b0 7
b0 G
b0 J
0-
05
08
b0 '
b0 F
b0 Y
b0 9
b0 I
b0 Q
b0 S
0;
0:
b0 3
b0 N
b0 P
b0 4
b0 H
b0 K
b0 6
b0 M
b0 O
0.
b0 "
b0 Z
0/
b0 #
b0 X
00
b0 $
b0 W
01
b0 %
b0 V
02
b0 &
b0 U
0(
0)
0*
0+
0,
b0 !
b0 R
b0 T
0=
0<
0>
b0 B
b0 L
0A
0C
0@
1E
0D
1?
#3
0E
#5
b1 7
b1 G
b1 J
1<
1D
#10
0D
#15
b10 7
b10 G
b10 J
b1 '
b1 F
b1 Y
b1 4
b1 H
b1 K
1D
#20
0D
#25
1,
b1 !
b1 R
b1 T
b1 9
b1 I
b1 Q
b1 S
18
b10 4
b10 H
b10 K
1D
#30
0D
#35
1D
b1 &
b1 U
#40
0D
#45
1D
b10 &
b10 U
#50
0D
#55
b11 7
b11 G
b11 J
1D
12
b11 &
b11 U
1-
#60
0D
#65
b100 7
b100 G
b100 J
0,
b0 !
b0 R
b0 T
b0 9
b0 I
b0 Q
b0 S
08
b10 '
b10 F
b10 Y
b11 4
b11 H
b11 K
1D
0-
#66
b0 &
b0 U
02
#70
0D
#75
1+
b10 !
b10 R
b10 T
18
b10 9
b10 I
b10 Q
b10 S
b100 4
b100 H
b100 K
1D
#80
0D
#85
1D
b1 %
b1 V
#90
0D
#95
1D
b10 %
b10 V
1-
#100
0D
#105
1D
b11 %
b11 V
0-
#110
0D
#115
b101 7
b101 G
b101 J
1D
11
b100 %
b100 V
#120
0D
#125
b110 7
b110 G
b110 J
0+
08
b11 '
b11 F
b11 Y
b0 !
b0 R
b0 T
b0 9
b0 I
b0 Q
b0 S
b101 4
b101 H
b101 K
1D
#126
b0 %
b0 V
01
#130
0D
#135
1*
b100 !
b100 R
b100 T
18
b11 9
b11 I
b11 Q
b11 S
b110 4
b110 H
b110 K
1D
1-
#140
0D
#145
1D
b1 $
b1 W
0-
#150
0D
#155
1D
b10 $
b10 W
#160
0D
#165
1D
b11 $
b11 W
#170
0D
#175
1D
b100 $
b100 W
1-
#180
0D
#185
b111 7
b111 G
b111 J
1D
10
b101 $
b101 W
0-
#190
0D
#195
b1000 7
b1000 G
b1000 J
0*
08
b0 !
b0 R
b0 T
b0 9
b0 I
b0 Q
b0 S
15
b100 '
b100 F
b100 Y
b111 4
b111 H
b111 K
1D
#196
b0 $
b0 W
00
#200
0D
#205
1)
b1000 !
b1000 R
b1000 T
b100 9
b100 I
b100 Q
b100 S
18
15
b100 '
b100 F
b100 Y
b1000 4
b1000 H
b1000 K
1D
#210
0D
#215
1D
1-
#216
b1 #
b1 X
#220
0D
#225
1D
0-
#226
b10 #
b10 X
#230
0D
#235
1D
#236
b11 #
b11 X
#240
0D
#245
1D
#246
b100 #
b100 X
#250
0D
#255
1D
1-
#256
b101 #
b101 X
#260
0D
#265
1D
0-
